{"models": [{"status": null, "delta_time": 1.0196471214294434, "nr_items": 500, "nr_orders": 1000, "profit": 151843.74500000002, "file_path": "/Users/matei/git/combinatorial_auction/data/datasets/groupe1/in190.txt", "name": "model_in190.txt", "solver": "AOCBaseSolution", "timeout": 60}, {"status": null, "delta_time": 1.1447248458862305, "nr_items": 500, "nr_orders": 1000, "profit": 178189.623, "file_path": "/Users/matei/git/combinatorial_auction/data/datasets/groupe1/in190.txt", "name": "model_in190.txt", "solver": "AOCBaseSolution", "timeout": 60}, {"status": null, "delta_time": 0.9853529930114746, "nr_items": 500, "nr_orders": 1000, "profit": 169608.387, "file_path": "/Users/matei/git/combinatorial_auction/data/datasets/groupe1/in190.txt", "name": "model_in190.txt", "solver": "AOCBaseSolution", "timeout": 60}, {"status": null, "delta_time": 1.4576389789581299, "nr_items": 500, "nr_orders": 1000, "profit": 256086.402, "file_path": "/Users/matei/git/combinatorial_auction/data/datasets/groupe1/in190.txt", "name": "model_in190.txt", "solver": "AOCBaseSolution", "timeout": 60}, {"status": null, "delta_time": 1.2172667980194092, "nr_items": 500, "nr_orders": 1000, "profit": 193558.30899999998, "file_path": "/Users/matei/git/combinatorial_auction/data/datasets/groupe1/in190.txt", "name": "model_in190.txt", "solver": "AOCBaseSolution", "timeout": 60}, {"status": null, "delta_time": 1.3659048080444336, "nr_items": 500, "nr_orders": 1000, "profit": 219325.594, "file_path": "/Users/matei/git/combinatorial_auction/data/datasets/groupe1/in142.txt", "name": "model_in142.txt", "solver": "AOCBaseSolution", "timeout": 60}, {"status": null, "delta_time": 1.1652030944824219, "nr_items": 500, "nr_orders": 1000, "profit": 204179.89899999998, "file_path": "/Users/matei/git/combinatorial_auction/data/datasets/groupe1/in142.txt", "name": "model_in142.txt", "solver": "AOCBaseSolution", "timeout": 60}, {"status": null, "delta_time": 1.1597046852111816, "nr_items": 500, "nr_orders": 1000, "profit": 177936.112, "file_path": "/Users/matei/git/combinatorial_auction/data/datasets/groupe1/in142.txt", "name": "model_in142.txt", "solver": "AOCBaseSolution", "timeout": 60}, {"status": null, "delta_time": 1.537597894668579, "nr_items": 500, "nr_orders": 1000, "profit": 212452.90800000002, "file_path": "/Users/matei/git/combinatorial_auction/data/datasets/groupe1/in142.txt", "name": "model_in142.txt", "solver": "AOCBaseSolution", "timeout": 60}, {"status": null, "delta_time": 1.0911149978637695, "nr_items": 500, "nr_orders": 1000, "profit": 154060.918, "file_path": "/Users/matei/git/combinatorial_auction/data/datasets/groupe1/in142.txt", "name": "model_in142.txt", "solver": "AOCBaseSolution", "timeout": 60}, {"status": null, "delta_time": 1.588974952697754, "nr_items": 500, "nr_orders": 1000, "profit": 166686.686, "file_path": "/Users/matei/git/combinatorial_auction/data/datasets/groupe1/in177.txt", "name": "model_in177.txt", "solver": "AOCBaseSolution", "timeout": 60}, {"status": null, "delta_time": 1.031648874282837, "nr_items": 500, "nr_orders": 1000, "profit": 155186.669, "file_path": "/Users/matei/git/combinatorial_auction/data/datasets/groupe1/in177.txt", "name": "model_in177.txt", "solver": "AOCBaseSolution", "timeout": 60}, {"status": null, "delta_time": 1.2940659523010254, "nr_items": 500, "nr_orders": 1000, "profit": 195953.02799999996, "file_path": "/Users/matei/git/combinatorial_auction/data/datasets/groupe1/in177.txt", "name": "model_in177.txt", "solver": "AOCBaseSolution", "timeout": 60}, {"status": null, "delta_time": 0.9047069549560547, "nr_items": 500, "nr_orders": 1000, "profit": 145353.252, "file_path": "/Users/matei/git/combinatorial_auction/data/datasets/groupe1/in177.txt", "name": "model_in177.txt", "solver": "AOCBaseSolution", "timeout": 60}, {"status": null, "delta_time": 0.8599948883056641, "nr_items": 500, "nr_orders": 1000, "profit": 140305.78699999998, "file_path": "/Users/matei/git/combinatorial_auction/data/datasets/groupe1/in177.txt", "name": "model_in177.txt", "solver": "AOCBaseSolution", "timeout": 60}, {"status": null, "delta_time": 0.9257841110229492, "nr_items": 500, "nr_orders": 1000, "profit": 132986.38700000002, "file_path": "/Users/matei/git/combinatorial_auction/data/datasets/groupe1/in131.txt", "name": "model_in131.txt", "solver": "AOCBaseSolution", "timeout": 60}, {"status": null, "delta_time": 0.9731981754302979, "nr_items": 500, "nr_orders": 1000, "profit": 138203.959, "file_path": "/Users/matei/git/combinatorial_auction/data/datasets/groupe1/in131.txt", "name": "model_in131.txt", "solver": "AOCBaseSolution", "timeout": 60}, {"status": null, "delta_time": 1.1743271350860596, "nr_items": 500, "nr_orders": 1000, "profit": 155228.47000000003, "file_path": "/Users/matei/git/combinatorial_auction/data/datasets/groupe1/in131.txt", "name": "model_in131.txt", "solver": "AOCBaseSolution", "timeout": 60}, {"status": null, "delta_time": 1.8257482051849365, "nr_items": 500, "nr_orders": 1000, "profit": 241838.82700000002, "file_path": "/Users/matei/git/combinatorial_auction/data/datasets/groupe1/in131.txt", "name": "model_in131.txt", "solver": "AOCBaseSolution", "timeout": 60}, {"status": null, "delta_time": 1.382284164428711, "nr_items": 500, "nr_orders": 1000, "profit": 205763.931, "file_path": "/Users/matei/git/combinatorial_auction/data/datasets/groupe1/in131.txt", "name": "model_in131.txt", "solver": "AOCBaseSolution", "timeout": 60}, {"status": null, "delta_time": 1.1136932373046875, "nr_items": 500, "nr_orders": 1000, "profit": 198714.261, "file_path": "/Users/matei/git/combinatorial_auction/data/datasets/groupe1/in162.txt", "name": "model_in162.txt", "solver": "AOCBaseSolution", "timeout": 60}, {"status": null, "delta_time": 0.8503742218017578, "nr_items": 500, "nr_orders": 1000, "profit": 134041.17999999996, "file_path": "/Users/matei/git/combinatorial_auction/data/datasets/groupe1/in162.txt", "name": "model_in162.txt", "solver": "AOCBaseSolution", "timeout": 60}, {"status": null, "delta_time": 1.3410158157348633, "nr_items": 500, "nr_orders": 1000, "profit": 192382.50999999998, "file_path": "/Users/matei/git/combinatorial_auction/data/datasets/groupe1/in162.txt", "name": "model_in162.txt", "solver": "AOCBaseSolution", "timeout": 60}, {"status": null, "delta_time": 1.0868360996246338, "nr_items": 500, "nr_orders": 1000, "profit": 141307.37, "file_path": "/Users/matei/git/combinatorial_auction/data/datasets/groupe1/in162.txt", "name": "model_in162.txt", "solver": "AOCBaseSolution", "timeout": 60}, {"status": null, "delta_time": 1.6190600395202637, "nr_items": 500, "nr_orders": 1000, "profit": 208734.331, "file_path": "/Users/matei/git/combinatorial_auction/data/datasets/groupe1/in162.txt", "name": "model_in162.txt", "solver": "AOCBaseSolution", "timeout": 60}, {"status": null, "delta_time": 1.09859299659729, "nr_items": 500, "nr_orders": 1000, "profit": 172592.394, "file_path": "/Users/matei/git/combinatorial_auction/data/datasets/groupe1/in182.txt", "name": "model_in182.txt", "solver": "AOCBaseSolution", "timeout": 60}, {"status": null, "delta_time": 1.4291279315948486, "nr_items": 500, "nr_orders": 1000, "profit": 165775.69500000004, "file_path": "/Users/matei/git/combinatorial_auction/data/datasets/groupe1/in182.txt", "name": "model_in182.txt", "solver": "AOCBaseSolution", "timeout": 60}, {"status": null, "delta_time": 1.3033349514007568, "nr_items": 500, "nr_orders": 1000, "profit": 133696.078, "file_path": "/Users/matei/git/combinatorial_auction/data/datasets/groupe1/in182.txt", "name": "model_in182.txt", "solver": "AOCBaseSolution", "timeout": 60}, {"status": null, "delta_time": 1.089491844177246, "nr_items": 500, "nr_orders": 1000, "profit": 154534.97699999998, "file_path": "/Users/matei/git/combinatorial_auction/data/datasets/groupe1/in182.txt", "name": "model_in182.txt", "solver": "AOCBaseSolution", "timeout": 60}, {"status": null, "delta_time": 0.9947061538696289, "nr_items": 500, "nr_orders": 1000, "profit": 137492.718, "file_path": "/Users/matei/git/combinatorial_auction/data/datasets/groupe1/in182.txt", "name": "model_in182.txt", "solver": "AOCBaseSolution", "timeout": 60}, {"status": null, "delta_time": 1.0340030193328857, "nr_items": 500, "nr_orders": 1000, "profit": 157784.19900000002, "file_path": "/Users/matei/git/combinatorial_auction/data/datasets/groupe1/in166.txt", "name": "model_in166.txt", "solver": "AOCBaseSolution", "timeout": 60}, {"status": null, "delta_time": 1.3030290603637695, "nr_items": 500, "nr_orders": 1000, "profit": 169534.93199999997, "file_path": "/Users/matei/git/combinatorial_auction/data/datasets/groupe1/in166.txt", "name": "model_in166.txt", "solver": "AOCBaseSolution", "timeout": 60}, {"status": null, "delta_time": 1.1967353820800781, "nr_items": 500, "nr_orders": 1000, "profit": 189175.21399999995, "file_path": "/Users/matei/git/combinatorial_auction/data/datasets/groupe1/in166.txt", "name": "model_in166.txt", "solver": "AOCBaseSolution", "timeout": 60}, {"status": null, "delta_time": 1.0048089027404785, "nr_items": 500, "nr_orders": 1000, "profit": 162732.33600000004, "file_path": "/Users/matei/git/combinatorial_auction/data/datasets/groupe1/in166.txt", "name": "model_in166.txt", "solver": "AOCBaseSolution", "timeout": 60}, {"status": null, "delta_time": 1.3739876747131348, "nr_items": 500, "nr_orders": 1000, "profit": 195663.87300000002, "file_path": "/Users/matei/git/combinatorial_auction/data/datasets/groupe1/in166.txt", "name": "model_in166.txt", "solver": "AOCBaseSolution", "timeout": 60}, {"status": null, "delta_time": 1.0179212093353271, "nr_items": 500, "nr_orders": 1000, "profit": 153945.61299999998, "file_path": "/Users/matei/git/combinatorial_auction/data/datasets/groupe1/in186.txt", "name": "model_in186.txt", "solver": "AOCBaseSolution", "timeout": 60}, {"status": null, "delta_time": 1.0461270809173584, "nr_items": 500, "nr_orders": 1000, "profit": 162683.252, "file_path": "/Users/matei/git/combinatorial_auction/data/datasets/groupe1/in186.txt", "name": "model_in186.txt", "solver": "AOCBaseSolution", "timeout": 60}, {"status": null, "delta_time": 1.4216551780700684, "nr_items": 500, "nr_orders": 1000, "profit": 200659.28800000003, "file_path": "/Users/matei/git/combinatorial_auction/data/datasets/groupe1/in186.txt", "name": "model_in186.txt", "solver": "AOCBaseSolution", "timeout": 60}, {"status": null, "delta_time": 1.0394210815429688, "nr_items": 500, "nr_orders": 1000, "profit": 173877.154, "file_path": "/Users/matei/git/combinatorial_auction/data/datasets/groupe1/in186.txt", "name": "model_in186.txt", "solver": "AOCBaseSolution", "timeout": 60}, {"status": null, "delta_time": 1.072402000427246, "nr_items": 500, "nr_orders": 1000, "profit": 165819.74400000004, "file_path": "/Users/matei/git/combinatorial_auction/data/datasets/groupe1/in186.txt", "name": "model_in186.txt", "solver": "AOCBaseSolution", "timeout": 60}, {"status": null, "delta_time": 1.2559831142425537, "nr_items": 500, "nr_orders": 1000, "profit": 182732.828, "file_path": "/Users/matei/git/combinatorial_auction/data/datasets/groupe1/in185.txt", "name": "model_in185.txt", "solver": "AOCBaseSolution", "timeout": 60}, {"status": null, "delta_time": 0.990837812423706, "nr_items": 500, "nr_orders": 1000, "profit": 128760.735, "file_path": "/Users/matei/git/combinatorial_auction/data/datasets/groupe1/in185.txt", "name": "model_in185.txt", "solver": "AOCBaseSolution", "timeout": 60}, {"status": null, "delta_time": 1.2300300598144531, "nr_items": 500, "nr_orders": 1000, "profit": 171744.63100000002, "file_path": "/Users/matei/git/combinatorial_auction/data/datasets/groupe1/in185.txt", "name": "model_in185.txt", "solver": "AOCBaseSolution", "timeout": 60}, {"status": null, "delta_time": 2.095233917236328, "nr_items": 500, "nr_orders": 1000, "profit": 279892.71300000005, "file_path": "/Users/matei/git/combinatorial_auction/data/datasets/groupe1/in185.txt", "name": "model_in185.txt", "solver": "AOCBaseSolution", "timeout": 60}, {"status": null, "delta_time": 0.9901938438415527, "nr_items": 500, "nr_orders": 1000, "profit": 128582.30500000001, "file_path": "/Users/matei/git/combinatorial_auction/data/datasets/groupe1/in185.txt", "name": "model_in185.txt", "solver": "AOCBaseSolution", "timeout": 60}, {"status": null, "delta_time": 1.5341308116912842, "nr_items": 500, "nr_orders": 1000, "profit": 239039.72500000003, "file_path": "/Users/matei/git/combinatorial_auction/data/datasets/groupe1/in120.txt", "name": "model_in120.txt", "solver": "AOCBaseSolution", "timeout": 60}, {"status": null, "delta_time": 0.9668347835540771, "nr_items": 500, "nr_orders": 1000, "profit": 136386.462, "file_path": "/Users/matei/git/combinatorial_auction/data/datasets/groupe1/in120.txt", "name": "model_in120.txt", "solver": "AOCBaseSolution", "timeout": 60}, {"status": null, "delta_time": 1.2003448009490967, "nr_items": 500, "nr_orders": 1000, "profit": 206363.84100000001, "file_path": "/Users/matei/git/combinatorial_auction/data/datasets/groupe1/in120.txt", "name": "model_in120.txt", "solver": "AOCBaseSolution", "timeout": 60}, {"status": null, "delta_time": 1.0874660015106201, "nr_items": 500, "nr_orders": 1000, "profit": 146642.745, "file_path": "/Users/matei/git/combinatorial_auction/data/datasets/groupe1/in120.txt", "name": "model_in120.txt", "solver": "AOCBaseSolution", "timeout": 60}, {"status": null, "delta_time": 0.919802188873291, "nr_items": 500, "nr_orders": 1000, "profit": 137430.039, "file_path": "/Users/matei/git/combinatorial_auction/data/datasets/groupe1/in120.txt", "name": "model_in120.txt", "solver": "AOCBaseSolution", "timeout": 60}, {"status": null, "delta_time": 1.5417938232421875, "nr_items": 500, "nr_orders": 1000, "profit": 239015.141, "file_path": "/Users/matei/git/combinatorial_auction/data/datasets/groupe1/in152.txt", "name": "model_in152.txt", "solver": "AOCBaseSolution", "timeout": 60}, {"status": null, "delta_time": 0.93874192237854, "nr_items": 500, "nr_orders": 1000, "profit": 141135.17799999999, "file_path": "/Users/matei/git/combinatorial_auction/data/datasets/groupe1/in152.txt", "name": "model_in152.txt", "solver": "AOCBaseSolution", "timeout": 60}, {"status": null, "delta_time": 0.9862868785858154, "nr_items": 500, "nr_orders": 1000, "profit": 151022.77199999997, "file_path": "/Users/matei/git/combinatorial_auction/data/datasets/groupe1/in152.txt", "name": "model_in152.txt", "solver": "AOCBaseSolution", "timeout": 60}, {"status": null, "delta_time": 1.6051490306854248, "nr_items": 500, "nr_orders": 1000, "profit": 235406.66900000005, "file_path": "/Users/matei/git/combinatorial_auction/data/datasets/groupe1/in152.txt", "name": "model_in152.txt", "solver": "AOCBaseSolution", "timeout": 60}, {"status": null, "delta_time": 1.3973040580749512, "nr_items": 500, "nr_orders": 1000, "profit": 183071.464, "file_path": "/Users/matei/git/combinatorial_auction/data/datasets/groupe1/in152.txt", "name": "model_in152.txt", "solver": "AOCBaseSolution", "timeout": 60}, {"status": null, "delta_time": 0.8372740745544434, "nr_items": 500, "nr_orders": 1000, "profit": 145805.371, "file_path": "/Users/matei/git/combinatorial_auction/data/datasets/groupe1/in154.txt", "name": "model_in154.txt", "solver": "AOCBaseSolution", "timeout": 60}, {"status": null, "delta_time": 0.8371100425720215, "nr_items": 500, "nr_orders": 1000, "profit": 141273.751, "file_path": "/Users/matei/git/combinatorial_auction/data/datasets/groupe1/in154.txt", "name": "model_in154.txt", "solver": "AOCBaseSolution", "timeout": 60}, {"status": null, "delta_time": 1.6304278373718262, "nr_items": 500, "nr_orders": 1000, "profit": 253328.59199999998, "file_path": "/Users/matei/git/combinatorial_auction/data/datasets/groupe1/in154.txt", "name": "model_in154.txt", "solver": "AOCBaseSolution", "timeout": 60}, {"status": null, "delta_time": 1.5836308002471924, "nr_items": 500, "nr_orders": 1000, "profit": 237767.17600000004, "file_path": "/Users/matei/git/combinatorial_auction/data/datasets/groupe1/in154.txt", "name": "model_in154.txt", "solver": "AOCBaseSolution", "timeout": 60}, {"status": null, "delta_time": 1.3358709812164307, "nr_items": 500, "nr_orders": 1000, "profit": 185819.08299999998, "file_path": "/Users/matei/git/combinatorial_auction/data/datasets/groupe1/in154.txt", "name": "model_in154.txt", "solver": "AOCBaseSolution", "timeout": 60}]}