{"models": [{"status": null, "delta_time": 0.09058666229248047, "nr_items": 1451, "nr_orders": 2000, "profit": 3338.0, "file_path": "/Users/matei/git/combinatorial_auction/data/datasets/CAST_test_instance/matching_40.txt", "name": "model_matching_40.txt", "solver": "AOCBaseSolution", "timeout": 300}, {"status": null, "delta_time": 0.08989787101745605, "nr_items": 1451, "nr_orders": 2000, "profit": 3530.0, "file_path": "/Users/matei/git/combinatorial_auction/data/datasets/CAST_test_instance/matching_40.txt", "name": "model_matching_40.txt", "solver": "AOCBaseSolution", "timeout": 300}, {"status": null, "delta_time": 0.0845329761505127, "nr_items": 1451, "nr_orders": 2000, "profit": 3703.0, "file_path": "/Users/matei/git/combinatorial_auction/data/datasets/CAST_test_instance/matching_40.txt", "name": "model_matching_40.txt", "solver": "AOCBaseSolution", "timeout": 300}, {"status": null, "delta_time": 0.08248114585876465, "nr_items": 1451, "nr_orders": 2000, "profit": 3330.0, "file_path": "/Users/matei/git/combinatorial_auction/data/datasets/CAST_test_instance/matching_40.txt", "name": "model_matching_40.txt", "solver": "AOCBaseSolution", "timeout": 300}, {"status": null, "delta_time": 0.07698702812194824, "nr_items": 1451, "nr_orders": 2000, "profit": 3402.0, "file_path": "/Users/matei/git/combinatorial_auction/data/datasets/CAST_test_instance/matching_40.txt", "name": "model_matching_40.txt", "solver": "AOCBaseSolution", "timeout": 300}, {"status": null, "delta_time": 0.07935094833374023, "nr_items": 1451, "nr_orders": 2000, "profit": 2690.0, "file_path": "/Users/matei/git/combinatorial_auction/data/datasets/CAST_test_instance/matching_40.txt", "name": "model_matching_40.txt", "solver": "AOCBaseSolution", "timeout": 300}, {"status": null, "delta_time": 0.07500290870666504, "nr_items": 1451, "nr_orders": 2000, "profit": 3721.0, "file_path": "/Users/matei/git/combinatorial_auction/data/datasets/CAST_test_instance/matching_40.txt", "name": "model_matching_40.txt", "solver": "AOCBaseSolution", "timeout": 300}, {"status": null, "delta_time": 0.07691597938537598, "nr_items": 1451, "nr_orders": 2000, "profit": 3551.0, "file_path": "/Users/matei/git/combinatorial_auction/data/datasets/CAST_test_instance/matching_40.txt", "name": "model_matching_40.txt", "solver": "AOCBaseSolution", "timeout": 300}, {"status": null, "delta_time": 0.08603405952453613, "nr_items": 1451, "nr_orders": 2000, "profit": 3756.0, "file_path": "/Users/matei/git/combinatorial_auction/data/datasets/CAST_test_instance/matching_40.txt", "name": "model_matching_40.txt", "solver": "AOCBaseSolution", "timeout": 300}, {"status": null, "delta_time": 0.07555317878723145, "nr_items": 1451, "nr_orders": 2000, "profit": 3554.0, "file_path": "/Users/matei/git/combinatorial_auction/data/datasets/CAST_test_instance/matching_40.txt", "name": "model_matching_40.txt", "solver": "AOCBaseSolution", "timeout": 300}, {"status": null, "delta_time": 0.08295083045959473, "nr_items": 1451, "nr_orders": 2000, "profit": 3802.0, "file_path": "/Users/matei/git/combinatorial_auction/data/datasets/CAST_test_instance/matching_40.txt", "name": "model_matching_40.txt", "solver": "AOCBaseSolution", "timeout": 300}, {"status": null, "delta_time": 0.07886195182800293, "nr_items": 1451, "nr_orders": 2000, "profit": 3727.0, "file_path": "/Users/matei/git/combinatorial_auction/data/datasets/CAST_test_instance/matching_40.txt", "name": "model_matching_40.txt", "solver": "AOCBaseSolution", "timeout": 300}, {"status": null, "delta_time": 0.07610082626342773, "nr_items": 1451, "nr_orders": 2000, "profit": 3884.0, "file_path": "/Users/matei/git/combinatorial_auction/data/datasets/CAST_test_instance/matching_40.txt", "name": "model_matching_40.txt", "solver": "AOCBaseSolution", "timeout": 300}, {"status": null, "delta_time": 0.0779719352722168, "nr_items": 1451, "nr_orders": 2000, "profit": 3526.0, "file_path": "/Users/matei/git/combinatorial_auction/data/datasets/CAST_test_instance/matching_40.txt", "name": "model_matching_40.txt", "solver": "AOCBaseSolution", "timeout": 300}, {"status": null, "delta_time": 0.0740518569946289, "nr_items": 1451, "nr_orders": 2000, "profit": 3411.0, "file_path": "/Users/matei/git/combinatorial_auction/data/datasets/CAST_test_instance/matching_40.txt", "name": "model_matching_40.txt", "solver": "AOCBaseSolution", "timeout": 300}, {"status": null, "delta_time": 0.08025288581848145, "nr_items": 1451, "nr_orders": 2000, "profit": 3655.0, "file_path": "/Users/matei/git/combinatorial_auction/data/datasets/CAST_test_instance/matching_40.txt", "name": "model_matching_40.txt", "solver": "AOCBaseSolution", "timeout": 300}, {"status": null, "delta_time": 0.09160900115966797, "nr_items": 1451, "nr_orders": 2000, "profit": 3604.0, "file_path": "/Users/matei/git/combinatorial_auction/data/datasets/CAST_test_instance/matching_40.txt", "name": "model_matching_40.txt", "solver": "AOCBaseSolution", "timeout": 300}, {"status": null, "delta_time": 0.07569694519042969, "nr_items": 1451, "nr_orders": 2000, "profit": 3978.0, "file_path": "/Users/matei/git/combinatorial_auction/data/datasets/CAST_test_instance/matching_40.txt", "name": "model_matching_40.txt", "solver": "AOCBaseSolution", "timeout": 300}, {"status": null, "delta_time": 0.07481694221496582, "nr_items": 1451, "nr_orders": 2000, "profit": 3638.0, "file_path": "/Users/matei/git/combinatorial_auction/data/datasets/CAST_test_instance/matching_40.txt", "name": "model_matching_40.txt", "solver": "AOCBaseSolution", "timeout": 300}, {"status": null, "delta_time": 0.07563591003417969, "nr_items": 1451, "nr_orders": 2000, "profit": 3759.0, "file_path": "/Users/matei/git/combinatorial_auction/data/datasets/CAST_test_instance/matching_40.txt", "name": "model_matching_40.txt", "solver": "AOCBaseSolution", "timeout": 300}, {"status": null, "delta_time": 0.0816502571105957, "nr_items": 1451, "nr_orders": 2000, "profit": 3576.0, "file_path": "/Users/matei/git/combinatorial_auction/data/datasets/CAST_test_instance/matching_40.txt", "name": "model_matching_40.txt", "solver": "AOCBaseSolution", "timeout": 300}, {"status": null, "delta_time": 0.07614493370056152, "nr_items": 1451, "nr_orders": 2000, "profit": 3503.0, "file_path": "/Users/matei/git/combinatorial_auction/data/datasets/CAST_test_instance/matching_40.txt", "name": "model_matching_40.txt", "solver": "AOCBaseSolution", "timeout": 300}, {"status": null, "delta_time": 0.07813715934753418, "nr_items": 1451, "nr_orders": 2000, "profit": 3694.0, "file_path": "/Users/matei/git/combinatorial_auction/data/datasets/CAST_test_instance/matching_40.txt", "name": "model_matching_40.txt", "solver": "AOCBaseSolution", "timeout": 300}, {"status": null, "delta_time": 0.07472109794616699, "nr_items": 1451, "nr_orders": 2000, "profit": 3502.0, "file_path": "/Users/matei/git/combinatorial_auction/data/datasets/CAST_test_instance/matching_40.txt", "name": "model_matching_40.txt", "solver": "AOCBaseSolution", "timeout": 300}, {"status": null, "delta_time": 0.07515287399291992, "nr_items": 1451, "nr_orders": 2000, "profit": 3968.0, "file_path": "/Users/matei/git/combinatorial_auction/data/datasets/CAST_test_instance/matching_40.txt", "name": "model_matching_40.txt", "solver": "AOCBaseSolution", "timeout": 300}, {"status": null, "delta_time": 0.07599496841430664, "nr_items": 1451, "nr_orders": 2000, "profit": 3550.0, "file_path": "/Users/matei/git/combinatorial_auction/data/datasets/CAST_test_instance/matching_40.txt", "name": "model_matching_40.txt", "solver": "AOCBaseSolution", "timeout": 300}, {"status": null, "delta_time": 0.08108329772949219, "nr_items": 1451, "nr_orders": 2000, "profit": 3922.0, "file_path": "/Users/matei/git/combinatorial_auction/data/datasets/CAST_test_instance/matching_40.txt", "name": "model_matching_40.txt", "solver": "AOCBaseSolution", "timeout": 300}, {"status": null, "delta_time": 0.07659101486206055, "nr_items": 1451, "nr_orders": 2000, "profit": 3731.0, "file_path": "/Users/matei/git/combinatorial_auction/data/datasets/CAST_test_instance/matching_40.txt", "name": "model_matching_40.txt", "solver": "AOCBaseSolution", "timeout": 300}, {"status": null, "delta_time": 0.08635187149047852, "nr_items": 1451, "nr_orders": 2000, "profit": 3568.0, "file_path": "/Users/matei/git/combinatorial_auction/data/datasets/CAST_test_instance/matching_40.txt", "name": "model_matching_40.txt", "solver": "AOCBaseSolution", "timeout": 300}, {"status": null, "delta_time": 0.0762948989868164, "nr_items": 1451, "nr_orders": 2000, "profit": 3182.0, "file_path": "/Users/matei/git/combinatorial_auction/data/datasets/CAST_test_instance/matching_40.txt", "name": "model_matching_40.txt", "solver": "AOCBaseSolution", "timeout": 300}, {"status": null, "delta_time": 0.11216616630554199, "nr_items": 1348, "nr_orders": 2000, "profit": 3654.0, "file_path": "/Users/matei/git/combinatorial_auction/data/datasets/CAST_test_instance/matching_80.txt", "name": "model_matching_80.txt", "solver": "AOCBaseSolution", "timeout": 300}, {"status": null, "delta_time": 0.1130228042602539, "nr_items": 1348, "nr_orders": 2000, "profit": 3735.0, "file_path": "/Users/matei/git/combinatorial_auction/data/datasets/CAST_test_instance/matching_80.txt", "name": "model_matching_80.txt", "solver": "AOCBaseSolution", "timeout": 300}, {"status": null, "delta_time": 0.12741398811340332, "nr_items": 1348, "nr_orders": 2000, "profit": 3854.0, "file_path": "/Users/matei/git/combinatorial_auction/data/datasets/CAST_test_instance/matching_80.txt", "name": "model_matching_80.txt", "solver": "AOCBaseSolution", "timeout": 300}, {"status": null, "delta_time": 0.09917712211608887, "nr_items": 1348, "nr_orders": 2000, "profit": 3780.0, "file_path": "/Users/matei/git/combinatorial_auction/data/datasets/CAST_test_instance/matching_80.txt", "name": "model_matching_80.txt", "solver": "AOCBaseSolution", "timeout": 300}, {"status": null, "delta_time": 0.09803295135498047, "nr_items": 1348, "nr_orders": 2000, "profit": 3787.0, "file_path": "/Users/matei/git/combinatorial_auction/data/datasets/CAST_test_instance/matching_80.txt", "name": "model_matching_80.txt", "solver": "AOCBaseSolution", "timeout": 300}, {"status": null, "delta_time": 0.10081672668457031, "nr_items": 1348, "nr_orders": 2000, "profit": 3463.0, "file_path": "/Users/matei/git/combinatorial_auction/data/datasets/CAST_test_instance/matching_80.txt", "name": "model_matching_80.txt", "solver": "AOCBaseSolution", "timeout": 300}, {"status": null, "delta_time": 0.0867459774017334, "nr_items": 1348, "nr_orders": 2000, "profit": 3536.0, "file_path": "/Users/matei/git/combinatorial_auction/data/datasets/CAST_test_instance/matching_80.txt", "name": "model_matching_80.txt", "solver": "AOCBaseSolution", "timeout": 300}, {"status": null, "delta_time": 0.08696413040161133, "nr_items": 1348, "nr_orders": 2000, "profit": 3437.0, "file_path": "/Users/matei/git/combinatorial_auction/data/datasets/CAST_test_instance/matching_80.txt", "name": "model_matching_80.txt", "solver": "AOCBaseSolution", "timeout": 300}, {"status": null, "delta_time": 0.09998202323913574, "nr_items": 1348, "nr_orders": 2000, "profit": 3756.0, "file_path": "/Users/matei/git/combinatorial_auction/data/datasets/CAST_test_instance/matching_80.txt", "name": "model_matching_80.txt", "solver": "AOCBaseSolution", "timeout": 300}, {"status": null, "delta_time": 0.09783601760864258, "nr_items": 1348, "nr_orders": 2000, "profit": 3856.0, "file_path": "/Users/matei/git/combinatorial_auction/data/datasets/CAST_test_instance/matching_80.txt", "name": "model_matching_80.txt", "solver": "AOCBaseSolution", "timeout": 300}, {"status": null, "delta_time": 0.09228181838989258, "nr_items": 1348, "nr_orders": 2000, "profit": 3106.0, "file_path": "/Users/matei/git/combinatorial_auction/data/datasets/CAST_test_instance/matching_80.txt", "name": "model_matching_80.txt", "solver": "AOCBaseSolution", "timeout": 300}, {"status": null, "delta_time": 0.10473918914794922, "nr_items": 1348, "nr_orders": 2000, "profit": 3523.0, "file_path": "/Users/matei/git/combinatorial_auction/data/datasets/CAST_test_instance/matching_80.txt", "name": "model_matching_80.txt", "solver": "AOCBaseSolution", "timeout": 300}, {"status": null, "delta_time": 0.09185385704040527, "nr_items": 1348, "nr_orders": 2000, "profit": 3092.0, "file_path": "/Users/matei/git/combinatorial_auction/data/datasets/CAST_test_instance/matching_80.txt", "name": "model_matching_80.txt", "solver": "AOCBaseSolution", "timeout": 300}, {"status": null, "delta_time": 0.09194493293762207, "nr_items": 1348, "nr_orders": 2000, "profit": 3517.0, "file_path": "/Users/matei/git/combinatorial_auction/data/datasets/CAST_test_instance/matching_80.txt", "name": "model_matching_80.txt", "solver": "AOCBaseSolution", "timeout": 300}, {"status": null, "delta_time": 0.09731292724609375, "nr_items": 1348, "nr_orders": 2000, "profit": 3501.0, "file_path": "/Users/matei/git/combinatorial_auction/data/datasets/CAST_test_instance/matching_80.txt", "name": "model_matching_80.txt", "solver": "AOCBaseSolution", "timeout": 300}, {"status": null, "delta_time": 0.09473609924316406, "nr_items": 1348, "nr_orders": 2000, "profit": 3689.0, "file_path": "/Users/matei/git/combinatorial_auction/data/datasets/CAST_test_instance/matching_80.txt", "name": "model_matching_80.txt", "solver": "AOCBaseSolution", "timeout": 300}, {"status": null, "delta_time": 0.1051180362701416, "nr_items": 1348, "nr_orders": 2000, "profit": 3511.0, "file_path": "/Users/matei/git/combinatorial_auction/data/datasets/CAST_test_instance/matching_80.txt", "name": "model_matching_80.txt", "solver": "AOCBaseSolution", "timeout": 300}, {"status": null, "delta_time": 0.11747503280639648, "nr_items": 1348, "nr_orders": 2000, "profit": 3956.0, "file_path": "/Users/matei/git/combinatorial_auction/data/datasets/CAST_test_instance/matching_80.txt", "name": "model_matching_80.txt", "solver": "AOCBaseSolution", "timeout": 300}, {"status": null, "delta_time": 0.11789894104003906, "nr_items": 1348, "nr_orders": 2000, "profit": 3837.0, "file_path": "/Users/matei/git/combinatorial_auction/data/datasets/CAST_test_instance/matching_80.txt", "name": "model_matching_80.txt", "solver": "AOCBaseSolution", "timeout": 300}, {"status": null, "delta_time": 0.10752320289611816, "nr_items": 1348, "nr_orders": 2000, "profit": 3354.0, "file_path": "/Users/matei/git/combinatorial_auction/data/datasets/CAST_test_instance/matching_80.txt", "name": "model_matching_80.txt", "solver": "AOCBaseSolution", "timeout": 300}, {"status": null, "delta_time": 0.10743999481201172, "nr_items": 1348, "nr_orders": 2000, "profit": 3759.0, "file_path": "/Users/matei/git/combinatorial_auction/data/datasets/CAST_test_instance/matching_80.txt", "name": "model_matching_80.txt", "solver": "AOCBaseSolution", "timeout": 300}, {"status": null, "delta_time": 0.1005859375, "nr_items": 1348, "nr_orders": 2000, "profit": 3524.0, "file_path": "/Users/matei/git/combinatorial_auction/data/datasets/CAST_test_instance/matching_80.txt", "name": "model_matching_80.txt", "solver": "AOCBaseSolution", "timeout": 300}, {"status": null, "delta_time": 0.1019737720489502, "nr_items": 1348, "nr_orders": 2000, "profit": 3758.0, "file_path": "/Users/matei/git/combinatorial_auction/data/datasets/CAST_test_instance/matching_80.txt", "name": "model_matching_80.txt", "solver": "AOCBaseSolution", "timeout": 300}, {"status": null, "delta_time": 0.08841490745544434, "nr_items": 1348, "nr_orders": 2000, "profit": 3531.0, "file_path": "/Users/matei/git/combinatorial_auction/data/datasets/CAST_test_instance/matching_80.txt", "name": "model_matching_80.txt", "solver": "AOCBaseSolution", "timeout": 300}, {"status": null, "delta_time": 0.07901597023010254, "nr_items": 1348, "nr_orders": 2000, "profit": 3396.0, "file_path": "/Users/matei/git/combinatorial_auction/data/datasets/CAST_test_instance/matching_80.txt", "name": "model_matching_80.txt", "solver": "AOCBaseSolution", "timeout": 300}, {"status": null, "delta_time": 0.08287191390991211, "nr_items": 1348, "nr_orders": 2000, "profit": 3575.0, "file_path": "/Users/matei/git/combinatorial_auction/data/datasets/CAST_test_instance/matching_80.txt", "name": "model_matching_80.txt", "solver": "AOCBaseSolution", "timeout": 300}, {"status": null, "delta_time": 0.08889889717102051, "nr_items": 1348, "nr_orders": 2000, "profit": 3484.0, "file_path": "/Users/matei/git/combinatorial_auction/data/datasets/CAST_test_instance/matching_80.txt", "name": "model_matching_80.txt", "solver": "AOCBaseSolution", "timeout": 300}, {"status": null, "delta_time": 0.11531996726989746, "nr_items": 1348, "nr_orders": 2000, "profit": 3620.0, "file_path": "/Users/matei/git/combinatorial_auction/data/datasets/CAST_test_instance/matching_80.txt", "name": "model_matching_80.txt", "solver": "AOCBaseSolution", "timeout": 300}, {"status": null, "delta_time": 0.07998275756835938, "nr_items": 1348, "nr_orders": 2000, "profit": 3524.0, "file_path": "/Users/matei/git/combinatorial_auction/data/datasets/CAST_test_instance/matching_80.txt", "name": "model_matching_80.txt", "solver": "AOCBaseSolution", "timeout": 300}, {"status": null, "delta_time": 0.08219003677368164, "nr_items": 1348, "nr_orders": 2000, "profit": 3328.0, "file_path": "/Users/matei/git/combinatorial_auction/data/datasets/CAST_test_instance/matching_80.txt", "name": "model_matching_80.txt", "solver": "AOCBaseSolution", "timeout": 300}, {"status": null, "delta_time": 0.0789182186126709, "nr_items": 1260, "nr_orders": 2000, "profit": 3901.0, "file_path": "/Users/matei/git/combinatorial_auction/data/datasets/CAST_test_instance/paths_40.txt", "name": "model_paths_40.txt", "solver": "AOCBaseSolution", "timeout": 300}, {"status": null, "delta_time": 0.08370614051818848, "nr_items": 1260, "nr_orders": 2000, "profit": 3855.0, "file_path": "/Users/matei/git/combinatorial_auction/data/datasets/CAST_test_instance/paths_40.txt", "name": "model_paths_40.txt", "solver": "AOCBaseSolution", "timeout": 300}, {"status": null, "delta_time": 0.10614800453186035, "nr_items": 1260, "nr_orders": 2000, "profit": 3652.0, "file_path": "/Users/matei/git/combinatorial_auction/data/datasets/CAST_test_instance/paths_40.txt", "name": "model_paths_40.txt", "solver": "AOCBaseSolution", "timeout": 300}, {"status": null, "delta_time": 0.08561992645263672, "nr_items": 1260, "nr_orders": 2000, "profit": 3433.0, "file_path": "/Users/matei/git/combinatorial_auction/data/datasets/CAST_test_instance/paths_40.txt", "name": "model_paths_40.txt", "solver": "AOCBaseSolution", "timeout": 300}, {"status": null, "delta_time": 0.08992528915405273, "nr_items": 1260, "nr_orders": 2000, "profit": 3493.0, "file_path": "/Users/matei/git/combinatorial_auction/data/datasets/CAST_test_instance/paths_40.txt", "name": "model_paths_40.txt", "solver": "AOCBaseSolution", "timeout": 300}, {"status": null, "delta_time": 0.0916588306427002, "nr_items": 1260, "nr_orders": 2000, "profit": 3335.0, "file_path": "/Users/matei/git/combinatorial_auction/data/datasets/CAST_test_instance/paths_40.txt", "name": "model_paths_40.txt", "solver": "AOCBaseSolution", "timeout": 300}, {"status": null, "delta_time": 0.11648702621459961, "nr_items": 1260, "nr_orders": 2000, "profit": 3073.0, "file_path": "/Users/matei/git/combinatorial_auction/data/datasets/CAST_test_instance/paths_40.txt", "name": "model_paths_40.txt", "solver": "AOCBaseSolution", "timeout": 300}, {"status": null, "delta_time": 0.11006903648376465, "nr_items": 1260, "nr_orders": 2000, "profit": 3815.0, "file_path": "/Users/matei/git/combinatorial_auction/data/datasets/CAST_test_instance/paths_40.txt", "name": "model_paths_40.txt", "solver": "AOCBaseSolution", "timeout": 300}, {"status": null, "delta_time": 0.11850214004516602, "nr_items": 1260, "nr_orders": 2000, "profit": 3820.0, "file_path": "/Users/matei/git/combinatorial_auction/data/datasets/CAST_test_instance/paths_40.txt", "name": "model_paths_40.txt", "solver": "AOCBaseSolution", "timeout": 300}, {"status": null, "delta_time": 0.10539388656616211, "nr_items": 1260, "nr_orders": 2000, "profit": 3894.0, "file_path": "/Users/matei/git/combinatorial_auction/data/datasets/CAST_test_instance/paths_40.txt", "name": "model_paths_40.txt", "solver": "AOCBaseSolution", "timeout": 300}, {"status": null, "delta_time": 0.09157299995422363, "nr_items": 1260, "nr_orders": 2000, "profit": 3830.0, "file_path": "/Users/matei/git/combinatorial_auction/data/datasets/CAST_test_instance/paths_40.txt", "name": "model_paths_40.txt", "solver": "AOCBaseSolution", "timeout": 300}, {"status": null, "delta_time": 0.11212587356567383, "nr_items": 1260, "nr_orders": 2000, "profit": 3496.0, "file_path": "/Users/matei/git/combinatorial_auction/data/datasets/CAST_test_instance/paths_40.txt", "name": "model_paths_40.txt", "solver": "AOCBaseSolution", "timeout": 300}, {"status": null, "delta_time": 0.1114959716796875, "nr_items": 1260, "nr_orders": 2000, "profit": 3262.0, "file_path": "/Users/matei/git/combinatorial_auction/data/datasets/CAST_test_instance/paths_40.txt", "name": "model_paths_40.txt", "solver": "AOCBaseSolution", "timeout": 300}, {"status": null, "delta_time": 0.08404088020324707, "nr_items": 1260, "nr_orders": 2000, "profit": 3601.0, "file_path": "/Users/matei/git/combinatorial_auction/data/datasets/CAST_test_instance/paths_40.txt", "name": "model_paths_40.txt", "solver": "AOCBaseSolution", "timeout": 300}, {"status": null, "delta_time": 0.09879302978515625, "nr_items": 1260, "nr_orders": 2000, "profit": 3850.0, "file_path": "/Users/matei/git/combinatorial_auction/data/datasets/CAST_test_instance/paths_40.txt", "name": "model_paths_40.txt", "solver": "AOCBaseSolution", "timeout": 300}, {"status": null, "delta_time": 0.08252787590026855, "nr_items": 1260, "nr_orders": 2000, "profit": 3775.0, "file_path": "/Users/matei/git/combinatorial_auction/data/datasets/CAST_test_instance/paths_40.txt", "name": "model_paths_40.txt", "solver": "AOCBaseSolution", "timeout": 300}, {"status": null, "delta_time": 0.09510970115661621, "nr_items": 1260, "nr_orders": 2000, "profit": 3661.0, "file_path": "/Users/matei/git/combinatorial_auction/data/datasets/CAST_test_instance/paths_40.txt", "name": "model_paths_40.txt", "solver": "AOCBaseSolution", "timeout": 300}, {"status": null, "delta_time": 0.09791207313537598, "nr_items": 1260, "nr_orders": 2000, "profit": 3788.0, "file_path": "/Users/matei/git/combinatorial_auction/data/datasets/CAST_test_instance/paths_40.txt", "name": "model_paths_40.txt", "solver": "AOCBaseSolution", "timeout": 300}, {"status": null, "delta_time": 0.09157490730285645, "nr_items": 1260, "nr_orders": 2000, "profit": 3257.0, "file_path": "/Users/matei/git/combinatorial_auction/data/datasets/CAST_test_instance/paths_40.txt", "name": "model_paths_40.txt", "solver": "AOCBaseSolution", "timeout": 300}, {"status": null, "delta_time": 0.0913839340209961, "nr_items": 1260, "nr_orders": 2000, "profit": 3363.0, "file_path": "/Users/matei/git/combinatorial_auction/data/datasets/CAST_test_instance/paths_40.txt", "name": "model_paths_40.txt", "solver": "AOCBaseSolution", "timeout": 300}, {"status": null, "delta_time": 0.09019184112548828, "nr_items": 1260, "nr_orders": 2000, "profit": 3733.0, "file_path": "/Users/matei/git/combinatorial_auction/data/datasets/CAST_test_instance/paths_40.txt", "name": "model_paths_40.txt", "solver": "AOCBaseSolution", "timeout": 300}, {"status": null, "delta_time": 0.0969698429107666, "nr_items": 1260, "nr_orders": 2000, "profit": 3477.0, "file_path": "/Users/matei/git/combinatorial_auction/data/datasets/CAST_test_instance/paths_40.txt", "name": "model_paths_40.txt", "solver": "AOCBaseSolution", "timeout": 300}, {"status": null, "delta_time": 0.08772993087768555, "nr_items": 1260, "nr_orders": 2000, "profit": 3432.0, "file_path": "/Users/matei/git/combinatorial_auction/data/datasets/CAST_test_instance/paths_40.txt", "name": "model_paths_40.txt", "solver": "AOCBaseSolution", "timeout": 300}, {"status": null, "delta_time": 0.08815193176269531, "nr_items": 1260, "nr_orders": 2000, "profit": 3405.0, "file_path": "/Users/matei/git/combinatorial_auction/data/datasets/CAST_test_instance/paths_40.txt", "name": "model_paths_40.txt", "solver": "AOCBaseSolution", "timeout": 300}, {"status": null, "delta_time": 0.10126209259033203, "nr_items": 1260, "nr_orders": 2000, "profit": 3604.0, "file_path": "/Users/matei/git/combinatorial_auction/data/datasets/CAST_test_instance/paths_40.txt", "name": "model_paths_40.txt", "solver": "AOCBaseSolution", "timeout": 300}, {"status": null, "delta_time": 0.09429073333740234, "nr_items": 1260, "nr_orders": 2000, "profit": 3743.0, "file_path": "/Users/matei/git/combinatorial_auction/data/datasets/CAST_test_instance/paths_40.txt", "name": "model_paths_40.txt", "solver": "AOCBaseSolution", "timeout": 300}, {"status": null, "delta_time": 0.08839607238769531, "nr_items": 1260, "nr_orders": 2000, "profit": 3479.0, "file_path": "/Users/matei/git/combinatorial_auction/data/datasets/CAST_test_instance/paths_40.txt", "name": "model_paths_40.txt", "solver": "AOCBaseSolution", "timeout": 300}, {"status": null, "delta_time": 0.10245895385742188, "nr_items": 1260, "nr_orders": 2000, "profit": 3627.0, "file_path": "/Users/matei/git/combinatorial_auction/data/datasets/CAST_test_instance/paths_40.txt", "name": "model_paths_40.txt", "solver": "AOCBaseSolution", "timeout": 300}, {"status": null, "delta_time": 0.08749103546142578, "nr_items": 1260, "nr_orders": 2000, "profit": 3705.0, "file_path": "/Users/matei/git/combinatorial_auction/data/datasets/CAST_test_instance/paths_40.txt", "name": "model_paths_40.txt", "solver": "AOCBaseSolution", "timeout": 300}, {"status": null, "delta_time": 0.09639286994934082, "nr_items": 1260, "nr_orders": 2000, "profit": 3888.0, "file_path": "/Users/matei/git/combinatorial_auction/data/datasets/CAST_test_instance/paths_40.txt", "name": "model_paths_40.txt", "solver": "AOCBaseSolution", "timeout": 300}, {"status": null, "delta_time": 0.08147883415222168, "nr_items": 1147, "nr_orders": 2000, "profit": 3621.0, "file_path": "/Users/matei/git/combinatorial_auction/data/datasets/CAST_test_instance/paths_100.txt", "name": "model_paths_100.txt", "solver": "AOCBaseSolution", "timeout": 300}, {"status": null, "delta_time": 0.08594870567321777, "nr_items": 1147, "nr_orders": 2000, "profit": 3626.0, "file_path": "/Users/matei/git/combinatorial_auction/data/datasets/CAST_test_instance/paths_100.txt", "name": "model_paths_100.txt", "solver": "AOCBaseSolution", "timeout": 300}, {"status": null, "delta_time": 0.08221173286437988, "nr_items": 1147, "nr_orders": 2000, "profit": 3355.0, "file_path": "/Users/matei/git/combinatorial_auction/data/datasets/CAST_test_instance/paths_100.txt", "name": "model_paths_100.txt", "solver": "AOCBaseSolution", "timeout": 300}, {"status": null, "delta_time": 0.08618974685668945, "nr_items": 1147, "nr_orders": 2000, "profit": 3303.0, "file_path": "/Users/matei/git/combinatorial_auction/data/datasets/CAST_test_instance/paths_100.txt", "name": "model_paths_100.txt", "solver": "AOCBaseSolution", "timeout": 300}, {"status": null, "delta_time": 0.08608222007751465, "nr_items": 1147, "nr_orders": 2000, "profit": 3687.0, "file_path": "/Users/matei/git/combinatorial_auction/data/datasets/CAST_test_instance/paths_100.txt", "name": "model_paths_100.txt", "solver": "AOCBaseSolution", "timeout": 300}, {"status": null, "delta_time": 0.0854499340057373, "nr_items": 1147, "nr_orders": 2000, "profit": 3894.0, "file_path": "/Users/matei/git/combinatorial_auction/data/datasets/CAST_test_instance/paths_100.txt", "name": "model_paths_100.txt", "solver": "AOCBaseSolution", "timeout": 300}, {"status": null, "delta_time": 0.08459711074829102, "nr_items": 1147, "nr_orders": 2000, "profit": 3618.0, "file_path": "/Users/matei/git/combinatorial_auction/data/datasets/CAST_test_instance/paths_100.txt", "name": "model_paths_100.txt", "solver": "AOCBaseSolution", "timeout": 300}, {"status": null, "delta_time": 0.09295892715454102, "nr_items": 1147, "nr_orders": 2000, "profit": 3574.0, "file_path": "/Users/matei/git/combinatorial_auction/data/datasets/CAST_test_instance/paths_100.txt", "name": "model_paths_100.txt", "solver": "AOCBaseSolution", "timeout": 300}, {"status": null, "delta_time": 0.09481024742126465, "nr_items": 1147, "nr_orders": 2000, "profit": 3657.0, "file_path": "/Users/matei/git/combinatorial_auction/data/datasets/CAST_test_instance/paths_100.txt", "name": "model_paths_100.txt", "solver": "AOCBaseSolution", "timeout": 300}, {"status": null, "delta_time": 0.10252881050109863, "nr_items": 1147, "nr_orders": 2000, "profit": 3641.0, "file_path": "/Users/matei/git/combinatorial_auction/data/datasets/CAST_test_instance/paths_100.txt", "name": "model_paths_100.txt", "solver": "AOCBaseSolution", "timeout": 300}, {"status": null, "delta_time": 0.09924912452697754, "nr_items": 1147, "nr_orders": 2000, "profit": 3177.0, "file_path": "/Users/matei/git/combinatorial_auction/data/datasets/CAST_test_instance/paths_100.txt", "name": "model_paths_100.txt", "solver": "AOCBaseSolution", "timeout": 300}, {"status": null, "delta_time": 0.0878911018371582, "nr_items": 1147, "nr_orders": 2000, "profit": 3834.0, "file_path": "/Users/matei/git/combinatorial_auction/data/datasets/CAST_test_instance/paths_100.txt", "name": "model_paths_100.txt", "solver": "AOCBaseSolution", "timeout": 300}, {"status": null, "delta_time": 0.08265900611877441, "nr_items": 1147, "nr_orders": 2000, "profit": 3678.0, "file_path": "/Users/matei/git/combinatorial_auction/data/datasets/CAST_test_instance/paths_100.txt", "name": "model_paths_100.txt", "solver": "AOCBaseSolution", "timeout": 300}, {"status": null, "delta_time": 0.0934600830078125, "nr_items": 1147, "nr_orders": 2000, "profit": 3354.0, "file_path": "/Users/matei/git/combinatorial_auction/data/datasets/CAST_test_instance/paths_100.txt", "name": "model_paths_100.txt", "solver": "AOCBaseSolution", "timeout": 300}, {"status": null, "delta_time": 0.08757233619689941, "nr_items": 1147, "nr_orders": 2000, "profit": 3328.0, "file_path": "/Users/matei/git/combinatorial_auction/data/datasets/CAST_test_instance/paths_100.txt", "name": "model_paths_100.txt", "solver": "AOCBaseSolution", "timeout": 300}, {"status": null, "delta_time": 0.08697772026062012, "nr_items": 1147, "nr_orders": 2000, "profit": 3803.0, "file_path": "/Users/matei/git/combinatorial_auction/data/datasets/CAST_test_instance/paths_100.txt", "name": "model_paths_100.txt", "solver": "AOCBaseSolution", "timeout": 300}, {"status": null, "delta_time": 0.09649991989135742, "nr_items": 1147, "nr_orders": 2000, "profit": 3014.0, "file_path": "/Users/matei/git/combinatorial_auction/data/datasets/CAST_test_instance/paths_100.txt", "name": "model_paths_100.txt", "solver": "AOCBaseSolution", "timeout": 300}, {"status": null, "delta_time": 0.08478903770446777, "nr_items": 1147, "nr_orders": 2000, "profit": 3304.0, "file_path": "/Users/matei/git/combinatorial_auction/data/datasets/CAST_test_instance/paths_100.txt", "name": "model_paths_100.txt", "solver": "AOCBaseSolution", "timeout": 300}, {"status": null, "delta_time": 0.09559988975524902, "nr_items": 1147, "nr_orders": 2000, "profit": 3047.0, "file_path": "/Users/matei/git/combinatorial_auction/data/datasets/CAST_test_instance/paths_100.txt", "name": "model_paths_100.txt", "solver": "AOCBaseSolution", "timeout": 300}, {"status": null, "delta_time": 0.08358621597290039, "nr_items": 1147, "nr_orders": 2000, "profit": 3930.0, "file_path": "/Users/matei/git/combinatorial_auction/data/datasets/CAST_test_instance/paths_100.txt", "name": "model_paths_100.txt", "solver": "AOCBaseSolution", "timeout": 300}, {"status": null, "delta_time": 0.08800888061523438, "nr_items": 1147, "nr_orders": 2000, "profit": 3478.0, "file_path": "/Users/matei/git/combinatorial_auction/data/datasets/CAST_test_instance/paths_100.txt", "name": "model_paths_100.txt", "solver": "AOCBaseSolution", "timeout": 300}, {"status": null, "delta_time": 0.09363913536071777, "nr_items": 1147, "nr_orders": 2000, "profit": 3186.0, "file_path": "/Users/matei/git/combinatorial_auction/data/datasets/CAST_test_instance/paths_100.txt", "name": "model_paths_100.txt", "solver": "AOCBaseSolution", "timeout": 300}, {"status": null, "delta_time": 0.08577990531921387, "nr_items": 1147, "nr_orders": 2000, "profit": 3592.0, "file_path": "/Users/matei/git/combinatorial_auction/data/datasets/CAST_test_instance/paths_100.txt", "name": "model_paths_100.txt", "solver": "AOCBaseSolution", "timeout": 300}, {"status": null, "delta_time": 0.09709477424621582, "nr_items": 1147, "nr_orders": 2000, "profit": 3508.0, "file_path": "/Users/matei/git/combinatorial_auction/data/datasets/CAST_test_instance/paths_100.txt", "name": "model_paths_100.txt", "solver": "AOCBaseSolution", "timeout": 300}, {"status": null, "delta_time": 0.08222222328186035, "nr_items": 1147, "nr_orders": 2000, "profit": 3239.0, "file_path": "/Users/matei/git/combinatorial_auction/data/datasets/CAST_test_instance/paths_100.txt", "name": "model_paths_100.txt", "solver": "AOCBaseSolution", "timeout": 300}, {"status": null, "delta_time": 0.08172178268432617, "nr_items": 1147, "nr_orders": 2000, "profit": 3649.0, "file_path": "/Users/matei/git/combinatorial_auction/data/datasets/CAST_test_instance/paths_100.txt", "name": "model_paths_100.txt", "solver": "AOCBaseSolution", "timeout": 300}, {"status": null, "delta_time": 0.09019780158996582, "nr_items": 1147, "nr_orders": 2000, "profit": 3585.0, "file_path": "/Users/matei/git/combinatorial_auction/data/datasets/CAST_test_instance/paths_100.txt", "name": "model_paths_100.txt", "solver": "AOCBaseSolution", "timeout": 300}, {"status": null, "delta_time": 0.08424115180969238, "nr_items": 1147, "nr_orders": 2000, "profit": 3626.0, "file_path": "/Users/matei/git/combinatorial_auction/data/datasets/CAST_test_instance/paths_100.txt", "name": "model_paths_100.txt", "solver": "AOCBaseSolution", "timeout": 300}, {"status": null, "delta_time": 0.08761811256408691, "nr_items": 1147, "nr_orders": 2000, "profit": 3375.0, "file_path": "/Users/matei/git/combinatorial_auction/data/datasets/CAST_test_instance/paths_100.txt", "name": "model_paths_100.txt", "solver": "AOCBaseSolution", "timeout": 300}, {"status": null, "delta_time": 0.08052611351013184, "nr_items": 1147, "nr_orders": 2000, "profit": 3397.0, "file_path": "/Users/matei/git/combinatorial_auction/data/datasets/CAST_test_instance/paths_100.txt", "name": "model_paths_100.txt", "solver": "AOCBaseSolution", "timeout": 300}, {"status": null, "delta_time": 0.08907508850097656, "nr_items": 278, "nr_orders": 2000, "profit": 3682.0, "file_path": "/Users/matei/git/combinatorial_auction/data/datasets/CAST_test_instance/scheduling_40.txt", "name": "model_scheduling_40.txt", "solver": "AOCBaseSolution", "timeout": 300}, {"status": null, "delta_time": 0.08464622497558594, "nr_items": 278, "nr_orders": 2000, "profit": 3194.0, "file_path": "/Users/matei/git/combinatorial_auction/data/datasets/CAST_test_instance/scheduling_40.txt", "name": "model_scheduling_40.txt", "solver": "AOCBaseSolution", "timeout": 300}, {"status": null, "delta_time": 0.08177995681762695, "nr_items": 278, "nr_orders": 2000, "profit": 3734.0, "file_path": "/Users/matei/git/combinatorial_auction/data/datasets/CAST_test_instance/scheduling_40.txt", "name": "model_scheduling_40.txt", "solver": "AOCBaseSolution", "timeout": 300}, {"status": null, "delta_time": 0.09444212913513184, "nr_items": 278, "nr_orders": 2000, "profit": 3739.0, "file_path": "/Users/matei/git/combinatorial_auction/data/datasets/CAST_test_instance/scheduling_40.txt", "name": "model_scheduling_40.txt", "solver": "AOCBaseSolution", "timeout": 300}, {"status": null, "delta_time": 0.08875393867492676, "nr_items": 278, "nr_orders": 2000, "profit": 3439.0, "file_path": "/Users/matei/git/combinatorial_auction/data/datasets/CAST_test_instance/scheduling_40.txt", "name": "model_scheduling_40.txt", "solver": "AOCBaseSolution", "timeout": 300}, {"status": null, "delta_time": 0.08730316162109375, "nr_items": 278, "nr_orders": 2000, "profit": 3654.0, "file_path": "/Users/matei/git/combinatorial_auction/data/datasets/CAST_test_instance/scheduling_40.txt", "name": "model_scheduling_40.txt", "solver": "AOCBaseSolution", "timeout": 300}, {"status": null, "delta_time": 0.08651614189147949, "nr_items": 278, "nr_orders": 2000, "profit": 3641.0, "file_path": "/Users/matei/git/combinatorial_auction/data/datasets/CAST_test_instance/scheduling_40.txt", "name": "model_scheduling_40.txt", "solver": "AOCBaseSolution", "timeout": 300}, {"status": null, "delta_time": 0.08562088012695312, "nr_items": 278, "nr_orders": 2000, "profit": 3842.0, "file_path": "/Users/matei/git/combinatorial_auction/data/datasets/CAST_test_instance/scheduling_40.txt", "name": "model_scheduling_40.txt", "solver": "AOCBaseSolution", "timeout": 300}, {"status": null, "delta_time": 0.08783793449401855, "nr_items": 278, "nr_orders": 2000, "profit": 3549.0, "file_path": "/Users/matei/git/combinatorial_auction/data/datasets/CAST_test_instance/scheduling_40.txt", "name": "model_scheduling_40.txt", "solver": "AOCBaseSolution", "timeout": 300}, {"status": null, "delta_time": 0.08713197708129883, "nr_items": 278, "nr_orders": 2000, "profit": 3442.0, "file_path": "/Users/matei/git/combinatorial_auction/data/datasets/CAST_test_instance/scheduling_40.txt", "name": "model_scheduling_40.txt", "solver": "AOCBaseSolution", "timeout": 300}, {"status": null, "delta_time": 0.08857607841491699, "nr_items": 278, "nr_orders": 2000, "profit": 3362.0, "file_path": "/Users/matei/git/combinatorial_auction/data/datasets/CAST_test_instance/scheduling_40.txt", "name": "model_scheduling_40.txt", "solver": "AOCBaseSolution", "timeout": 300}, {"status": null, "delta_time": 0.08846426010131836, "nr_items": 278, "nr_orders": 2000, "profit": 3291.0, "file_path": "/Users/matei/git/combinatorial_auction/data/datasets/CAST_test_instance/scheduling_40.txt", "name": "model_scheduling_40.txt", "solver": "AOCBaseSolution", "timeout": 300}, {"status": null, "delta_time": 0.08857989311218262, "nr_items": 278, "nr_orders": 2000, "profit": 3749.0, "file_path": "/Users/matei/git/combinatorial_auction/data/datasets/CAST_test_instance/scheduling_40.txt", "name": "model_scheduling_40.txt", "solver": "AOCBaseSolution", "timeout": 300}, {"status": null, "delta_time": 0.09469008445739746, "nr_items": 278, "nr_orders": 2000, "profit": 3534.0, "file_path": "/Users/matei/git/combinatorial_auction/data/datasets/CAST_test_instance/scheduling_40.txt", "name": "model_scheduling_40.txt", "solver": "AOCBaseSolution", "timeout": 300}, {"status": null, "delta_time": 0.0895681381225586, "nr_items": 278, "nr_orders": 2000, "profit": 3638.0, "file_path": "/Users/matei/git/combinatorial_auction/data/datasets/CAST_test_instance/scheduling_40.txt", "name": "model_scheduling_40.txt", "solver": "AOCBaseSolution", "timeout": 300}, {"status": null, "delta_time": 0.08904290199279785, "nr_items": 278, "nr_orders": 2000, "profit": 3330.0, "file_path": "/Users/matei/git/combinatorial_auction/data/datasets/CAST_test_instance/scheduling_40.txt", "name": "model_scheduling_40.txt", "solver": "AOCBaseSolution", "timeout": 300}, {"status": null, "delta_time": 0.08661890029907227, "nr_items": 278, "nr_orders": 2000, "profit": 3213.0, "file_path": "/Users/matei/git/combinatorial_auction/data/datasets/CAST_test_instance/scheduling_40.txt", "name": "model_scheduling_40.txt", "solver": "AOCBaseSolution", "timeout": 300}, {"status": null, "delta_time": 0.09024882316589355, "nr_items": 278, "nr_orders": 2000, "profit": 3602.0, "file_path": "/Users/matei/git/combinatorial_auction/data/datasets/CAST_test_instance/scheduling_40.txt", "name": "model_scheduling_40.txt", "solver": "AOCBaseSolution", "timeout": 300}, {"status": null, "delta_time": 0.08740592002868652, "nr_items": 278, "nr_orders": 2000, "profit": 3497.0, "file_path": "/Users/matei/git/combinatorial_auction/data/datasets/CAST_test_instance/scheduling_40.txt", "name": "model_scheduling_40.txt", "solver": "AOCBaseSolution", "timeout": 300}, {"status": null, "delta_time": 0.08753395080566406, "nr_items": 278, "nr_orders": 2000, "profit": 3711.0, "file_path": "/Users/matei/git/combinatorial_auction/data/datasets/CAST_test_instance/scheduling_40.txt", "name": "model_scheduling_40.txt", "solver": "AOCBaseSolution", "timeout": 300}, {"status": null, "delta_time": 0.09365320205688477, "nr_items": 278, "nr_orders": 2000, "profit": 3667.0, "file_path": "/Users/matei/git/combinatorial_auction/data/datasets/CAST_test_instance/scheduling_40.txt", "name": "model_scheduling_40.txt", "solver": "AOCBaseSolution", "timeout": 300}, {"status": null, "delta_time": 0.08655190467834473, "nr_items": 278, "nr_orders": 2000, "profit": 3897.0, "file_path": "/Users/matei/git/combinatorial_auction/data/datasets/CAST_test_instance/scheduling_40.txt", "name": "model_scheduling_40.txt", "solver": "AOCBaseSolution", "timeout": 300}, {"status": null, "delta_time": 0.08635711669921875, "nr_items": 278, "nr_orders": 2000, "profit": 3452.0, "file_path": "/Users/matei/git/combinatorial_auction/data/datasets/CAST_test_instance/scheduling_40.txt", "name": "model_scheduling_40.txt", "solver": "AOCBaseSolution", "timeout": 300}, {"status": null, "delta_time": 0.09616303443908691, "nr_items": 278, "nr_orders": 2000, "profit": 3526.0, "file_path": "/Users/matei/git/combinatorial_auction/data/datasets/CAST_test_instance/scheduling_40.txt", "name": "model_scheduling_40.txt", "solver": "AOCBaseSolution", "timeout": 300}, {"status": null, "delta_time": 0.09915423393249512, "nr_items": 278, "nr_orders": 2000, "profit": 3165.0, "file_path": "/Users/matei/git/combinatorial_auction/data/datasets/CAST_test_instance/scheduling_40.txt", "name": "model_scheduling_40.txt", "solver": "AOCBaseSolution", "timeout": 300}, {"status": null, "delta_time": 0.08869791030883789, "nr_items": 278, "nr_orders": 2000, "profit": 3737.0, "file_path": "/Users/matei/git/combinatorial_auction/data/datasets/CAST_test_instance/scheduling_40.txt", "name": "model_scheduling_40.txt", "solver": "AOCBaseSolution", "timeout": 300}, {"status": null, "delta_time": 0.08995389938354492, "nr_items": 278, "nr_orders": 2000, "profit": 3853.0, "file_path": "/Users/matei/git/combinatorial_auction/data/datasets/CAST_test_instance/scheduling_40.txt", "name": "model_scheduling_40.txt", "solver": "AOCBaseSolution", "timeout": 300}, {"status": null, "delta_time": 0.08849787712097168, "nr_items": 278, "nr_orders": 2000, "profit": 3621.0, "file_path": "/Users/matei/git/combinatorial_auction/data/datasets/CAST_test_instance/scheduling_40.txt", "name": "model_scheduling_40.txt", "solver": "AOCBaseSolution", "timeout": 300}, {"status": null, "delta_time": 0.0884239673614502, "nr_items": 278, "nr_orders": 2000, "profit": 3298.0, "file_path": "/Users/matei/git/combinatorial_auction/data/datasets/CAST_test_instance/scheduling_40.txt", "name": "model_scheduling_40.txt", "solver": "AOCBaseSolution", "timeout": 300}, {"status": null, "delta_time": 0.09264707565307617, "nr_items": 278, "nr_orders": 2000, "profit": 3750.0, "file_path": "/Users/matei/git/combinatorial_auction/data/datasets/CAST_test_instance/scheduling_40.txt", "name": "model_scheduling_40.txt", "solver": "AOCBaseSolution", "timeout": 300}, {"status": null, "delta_time": 0.08566570281982422, "nr_items": 208, "nr_orders": 2000, "profit": 3558.0, "file_path": "/Users/matei/git/combinatorial_auction/data/datasets/CAST_test_instance/scheduling_100.txt", "name": "model_scheduling_100.txt", "solver": "AOCBaseSolution", "timeout": 300}, {"status": null, "delta_time": 0.08551502227783203, "nr_items": 208, "nr_orders": 2000, "profit": 3510.0, "file_path": "/Users/matei/git/combinatorial_auction/data/datasets/CAST_test_instance/scheduling_100.txt", "name": "model_scheduling_100.txt", "solver": "AOCBaseSolution", "timeout": 300}, {"status": null, "delta_time": 0.08789610862731934, "nr_items": 208, "nr_orders": 2000, "profit": 3513.0, "file_path": "/Users/matei/git/combinatorial_auction/data/datasets/CAST_test_instance/scheduling_100.txt", "name": "model_scheduling_100.txt", "solver": "AOCBaseSolution", "timeout": 300}, {"status": null, "delta_time": 0.0852510929107666, "nr_items": 208, "nr_orders": 2000, "profit": 3910.0, "file_path": "/Users/matei/git/combinatorial_auction/data/datasets/CAST_test_instance/scheduling_100.txt", "name": "model_scheduling_100.txt", "solver": "AOCBaseSolution", "timeout": 300}, {"status": null, "delta_time": 0.08336591720581055, "nr_items": 208, "nr_orders": 2000, "profit": 3544.0, "file_path": "/Users/matei/git/combinatorial_auction/data/datasets/CAST_test_instance/scheduling_100.txt", "name": "model_scheduling_100.txt", "solver": "AOCBaseSolution", "timeout": 300}, {"status": null, "delta_time": 0.08207201957702637, "nr_items": 208, "nr_orders": 2000, "profit": 3892.0, "file_path": "/Users/matei/git/combinatorial_auction/data/datasets/CAST_test_instance/scheduling_100.txt", "name": "model_scheduling_100.txt", "solver": "AOCBaseSolution", "timeout": 300}, {"status": null, "delta_time": 0.0998220443725586, "nr_items": 208, "nr_orders": 2000, "profit": 3561.0, "file_path": "/Users/matei/git/combinatorial_auction/data/datasets/CAST_test_instance/scheduling_100.txt", "name": "model_scheduling_100.txt", "solver": "AOCBaseSolution", "timeout": 300}, {"status": null, "delta_time": 0.0984199047088623, "nr_items": 208, "nr_orders": 2000, "profit": 3741.0, "file_path": "/Users/matei/git/combinatorial_auction/data/datasets/CAST_test_instance/scheduling_100.txt", "name": "model_scheduling_100.txt", "solver": "AOCBaseSolution", "timeout": 300}, {"status": null, "delta_time": 0.0879521369934082, "nr_items": 208, "nr_orders": 2000, "profit": 3290.0, "file_path": "/Users/matei/git/combinatorial_auction/data/datasets/CAST_test_instance/scheduling_100.txt", "name": "model_scheduling_100.txt", "solver": "AOCBaseSolution", "timeout": 300}, {"status": null, "delta_time": 0.08953189849853516, "nr_items": 208, "nr_orders": 2000, "profit": 3862.0, "file_path": "/Users/matei/git/combinatorial_auction/data/datasets/CAST_test_instance/scheduling_100.txt", "name": "model_scheduling_100.txt", "solver": "AOCBaseSolution", "timeout": 300}, {"status": null, "delta_time": 0.0836639404296875, "nr_items": 208, "nr_orders": 2000, "profit": 3281.0, "file_path": "/Users/matei/git/combinatorial_auction/data/datasets/CAST_test_instance/scheduling_100.txt", "name": "model_scheduling_100.txt", "solver": "AOCBaseSolution", "timeout": 300}, {"status": null, "delta_time": 0.09204506874084473, "nr_items": 208, "nr_orders": 2000, "profit": 3863.0, "file_path": "/Users/matei/git/combinatorial_auction/data/datasets/CAST_test_instance/scheduling_100.txt", "name": "model_scheduling_100.txt", "solver": "AOCBaseSolution", "timeout": 300}, {"status": null, "delta_time": 0.11485505104064941, "nr_items": 208, "nr_orders": 2000, "profit": 3802.0, "file_path": "/Users/matei/git/combinatorial_auction/data/datasets/CAST_test_instance/scheduling_100.txt", "name": "model_scheduling_100.txt", "solver": "AOCBaseSolution", "timeout": 300}, {"status": null, "delta_time": 0.09291291236877441, "nr_items": 208, "nr_orders": 2000, "profit": 3655.0, "file_path": "/Users/matei/git/combinatorial_auction/data/datasets/CAST_test_instance/scheduling_100.txt", "name": "model_scheduling_100.txt", "solver": "AOCBaseSolution", "timeout": 300}, {"status": null, "delta_time": 0.10198307037353516, "nr_items": 208, "nr_orders": 2000, "profit": 3747.0, "file_path": "/Users/matei/git/combinatorial_auction/data/datasets/CAST_test_instance/scheduling_100.txt", "name": "model_scheduling_100.txt", "solver": "AOCBaseSolution", "timeout": 300}, {"status": null, "delta_time": 0.10275006294250488, "nr_items": 208, "nr_orders": 2000, "profit": 3498.0, "file_path": "/Users/matei/git/combinatorial_auction/data/datasets/CAST_test_instance/scheduling_100.txt", "name": "model_scheduling_100.txt", "solver": "AOCBaseSolution", "timeout": 300}, {"status": null, "delta_time": 0.09252619743347168, "nr_items": 208, "nr_orders": 2000, "profit": 3506.0, "file_path": "/Users/matei/git/combinatorial_auction/data/datasets/CAST_test_instance/scheduling_100.txt", "name": "model_scheduling_100.txt", "solver": "AOCBaseSolution", "timeout": 300}, {"status": null, "delta_time": 0.08751082420349121, "nr_items": 208, "nr_orders": 2000, "profit": 3293.0, "file_path": "/Users/matei/git/combinatorial_auction/data/datasets/CAST_test_instance/scheduling_100.txt", "name": "model_scheduling_100.txt", "solver": "AOCBaseSolution", "timeout": 300}, {"status": null, "delta_time": 0.1057579517364502, "nr_items": 208, "nr_orders": 2000, "profit": 3334.0, "file_path": "/Users/matei/git/combinatorial_auction/data/datasets/CAST_test_instance/scheduling_100.txt", "name": "model_scheduling_100.txt", "solver": "AOCBaseSolution", "timeout": 300}, {"status": null, "delta_time": 0.08926510810852051, "nr_items": 208, "nr_orders": 2000, "profit": 3472.0, "file_path": "/Users/matei/git/combinatorial_auction/data/datasets/CAST_test_instance/scheduling_100.txt", "name": "model_scheduling_100.txt", "solver": "AOCBaseSolution", "timeout": 300}, {"status": null, "delta_time": 0.09661221504211426, "nr_items": 208, "nr_orders": 2000, "profit": 3751.0, "file_path": "/Users/matei/git/combinatorial_auction/data/datasets/CAST_test_instance/scheduling_100.txt", "name": "model_scheduling_100.txt", "solver": "AOCBaseSolution", "timeout": 300}, {"status": null, "delta_time": 0.09129190444946289, "nr_items": 208, "nr_orders": 2000, "profit": 3736.0, "file_path": "/Users/matei/git/combinatorial_auction/data/datasets/CAST_test_instance/scheduling_100.txt", "name": "model_scheduling_100.txt", "solver": "AOCBaseSolution", "timeout": 300}, {"status": null, "delta_time": 0.09250712394714355, "nr_items": 208, "nr_orders": 2000, "profit": 3343.0, "file_path": "/Users/matei/git/combinatorial_auction/data/datasets/CAST_test_instance/scheduling_100.txt", "name": "model_scheduling_100.txt", "solver": "AOCBaseSolution", "timeout": 300}, {"status": null, "delta_time": 0.10492801666259766, "nr_items": 208, "nr_orders": 2000, "profit": 3528.0, "file_path": "/Users/matei/git/combinatorial_auction/data/datasets/CAST_test_instance/scheduling_100.txt", "name": "model_scheduling_100.txt", "solver": "AOCBaseSolution", "timeout": 300}, {"status": null, "delta_time": 0.10761594772338867, "nr_items": 208, "nr_orders": 2000, "profit": 3834.0, "file_path": "/Users/matei/git/combinatorial_auction/data/datasets/CAST_test_instance/scheduling_100.txt", "name": "model_scheduling_100.txt", "solver": "AOCBaseSolution", "timeout": 300}, {"status": null, "delta_time": 0.11613011360168457, "nr_items": 208, "nr_orders": 2000, "profit": 3756.0, "file_path": "/Users/matei/git/combinatorial_auction/data/datasets/CAST_test_instance/scheduling_100.txt", "name": "model_scheduling_100.txt", "solver": "AOCBaseSolution", "timeout": 300}, {"status": null, "delta_time": 0.10452413558959961, "nr_items": 208, "nr_orders": 2000, "profit": 3063.0, "file_path": "/Users/matei/git/combinatorial_auction/data/datasets/CAST_test_instance/scheduling_100.txt", "name": "model_scheduling_100.txt", "solver": "AOCBaseSolution", "timeout": 300}, {"status": null, "delta_time": 0.0924079418182373, "nr_items": 208, "nr_orders": 2000, "profit": 3478.0, "file_path": "/Users/matei/git/combinatorial_auction/data/datasets/CAST_test_instance/scheduling_100.txt", "name": "model_scheduling_100.txt", "solver": "AOCBaseSolution", "timeout": 300}, {"status": null, "delta_time": 0.0950469970703125, "nr_items": 208, "nr_orders": 2000, "profit": 3577.0, "file_path": "/Users/matei/git/combinatorial_auction/data/datasets/CAST_test_instance/scheduling_100.txt", "name": "model_scheduling_100.txt", "solver": "AOCBaseSolution", "timeout": 300}, {"status": null, "delta_time": 0.10611200332641602, "nr_items": 208, "nr_orders": 2000, "profit": 3694.0, "file_path": "/Users/matei/git/combinatorial_auction/data/datasets/CAST_test_instance/scheduling_100.txt", "name": "model_scheduling_100.txt", "solver": "AOCBaseSolution", "timeout": 300}, {"status": null, "delta_time": 0.09934091567993164, "nr_items": 2408, "nr_orders": 2000, "profit": 3448.0, "file_path": "/Users/matei/git/combinatorial_auction/data/datasets/CAST_test_instance/arbitrary_40.txt", "name": "model_arbitrary_40.txt", "solver": "AOCBaseSolution", "timeout": 300}, {"status": null, "delta_time": 0.1067659854888916, "nr_items": 2408, "nr_orders": 2000, "profit": 3724.0, "file_path": "/Users/matei/git/combinatorial_auction/data/datasets/CAST_test_instance/arbitrary_40.txt", "name": "model_arbitrary_40.txt", "solver": "AOCBaseSolution", "timeout": 300}, {"status": null, "delta_time": 0.09760689735412598, "nr_items": 2408, "nr_orders": 2000, "profit": 3811.0, "file_path": "/Users/matei/git/combinatorial_auction/data/datasets/CAST_test_instance/arbitrary_40.txt", "name": "model_arbitrary_40.txt", "solver": "AOCBaseSolution", "timeout": 300}, {"status": null, "delta_time": 0.09961485862731934, "nr_items": 2408, "nr_orders": 2000, "profit": 3326.0, "file_path": "/Users/matei/git/combinatorial_auction/data/datasets/CAST_test_instance/arbitrary_40.txt", "name": "model_arbitrary_40.txt", "solver": "AOCBaseSolution", "timeout": 300}, {"status": null, "delta_time": 0.10345816612243652, "nr_items": 2408, "nr_orders": 2000, "profit": 3547.0, "file_path": "/Users/matei/git/combinatorial_auction/data/datasets/CAST_test_instance/arbitrary_40.txt", "name": "model_arbitrary_40.txt", "solver": "AOCBaseSolution", "timeout": 300}, {"status": null, "delta_time": 0.1073157787322998, "nr_items": 2408, "nr_orders": 2000, "profit": 3624.0, "file_path": "/Users/matei/git/combinatorial_auction/data/datasets/CAST_test_instance/arbitrary_40.txt", "name": "model_arbitrary_40.txt", "solver": "AOCBaseSolution", "timeout": 300}, {"status": null, "delta_time": 0.09823727607727051, "nr_items": 2408, "nr_orders": 2000, "profit": 3495.0, "file_path": "/Users/matei/git/combinatorial_auction/data/datasets/CAST_test_instance/arbitrary_40.txt", "name": "model_arbitrary_40.txt", "solver": "AOCBaseSolution", "timeout": 300}, {"status": null, "delta_time": 0.1018519401550293, "nr_items": 2408, "nr_orders": 2000, "profit": 3637.0, "file_path": "/Users/matei/git/combinatorial_auction/data/datasets/CAST_test_instance/arbitrary_40.txt", "name": "model_arbitrary_40.txt", "solver": "AOCBaseSolution", "timeout": 300}, {"status": null, "delta_time": 0.0987241268157959, "nr_items": 2408, "nr_orders": 2000, "profit": 3730.0, "file_path": "/Users/matei/git/combinatorial_auction/data/datasets/CAST_test_instance/arbitrary_40.txt", "name": "model_arbitrary_40.txt", "solver": "AOCBaseSolution", "timeout": 300}, {"status": null, "delta_time": 0.10637092590332031, "nr_items": 2408, "nr_orders": 2000, "profit": 3521.0, "file_path": "/Users/matei/git/combinatorial_auction/data/datasets/CAST_test_instance/arbitrary_40.txt", "name": "model_arbitrary_40.txt", "solver": "AOCBaseSolution", "timeout": 300}, {"status": null, "delta_time": 0.09859800338745117, "nr_items": 2408, "nr_orders": 2000, "profit": 3590.0, "file_path": "/Users/matei/git/combinatorial_auction/data/datasets/CAST_test_instance/arbitrary_40.txt", "name": "model_arbitrary_40.txt", "solver": "AOCBaseSolution", "timeout": 300}, {"status": null, "delta_time": 0.10390400886535645, "nr_items": 2408, "nr_orders": 2000, "profit": 3753.0, "file_path": "/Users/matei/git/combinatorial_auction/data/datasets/CAST_test_instance/arbitrary_40.txt", "name": "model_arbitrary_40.txt", "solver": "AOCBaseSolution", "timeout": 300}, {"status": null, "delta_time": 0.10896086692810059, "nr_items": 2408, "nr_orders": 2000, "profit": 3750.0, "file_path": "/Users/matei/git/combinatorial_auction/data/datasets/CAST_test_instance/arbitrary_40.txt", "name": "model_arbitrary_40.txt", "solver": "AOCBaseSolution", "timeout": 300}, {"status": null, "delta_time": 0.1053781509399414, "nr_items": 2408, "nr_orders": 2000, "profit": 3593.0, "file_path": "/Users/matei/git/combinatorial_auction/data/datasets/CAST_test_instance/arbitrary_40.txt", "name": "model_arbitrary_40.txt", "solver": "AOCBaseSolution", "timeout": 300}, {"status": null, "delta_time": 0.1002962589263916, "nr_items": 2408, "nr_orders": 2000, "profit": 3427.0, "file_path": "/Users/matei/git/combinatorial_auction/data/datasets/CAST_test_instance/arbitrary_40.txt", "name": "model_arbitrary_40.txt", "solver": "AOCBaseSolution", "timeout": 300}, {"status": null, "delta_time": 0.09922027587890625, "nr_items": 2408, "nr_orders": 2000, "profit": 3014.0, "file_path": "/Users/matei/git/combinatorial_auction/data/datasets/CAST_test_instance/arbitrary_40.txt", "name": "model_arbitrary_40.txt", "solver": "AOCBaseSolution", "timeout": 300}, {"status": null, "delta_time": 0.09963703155517578, "nr_items": 2408, "nr_orders": 2000, "profit": 3599.0, "file_path": "/Users/matei/git/combinatorial_auction/data/datasets/CAST_test_instance/arbitrary_40.txt", "name": "model_arbitrary_40.txt", "solver": "AOCBaseSolution", "timeout": 300}, {"status": null, "delta_time": 0.098876953125, "nr_items": 2408, "nr_orders": 2000, "profit": 3555.0, "file_path": "/Users/matei/git/combinatorial_auction/data/datasets/CAST_test_instance/arbitrary_40.txt", "name": "model_arbitrary_40.txt", "solver": "AOCBaseSolution", "timeout": 300}, {"status": null, "delta_time": 0.11129093170166016, "nr_items": 2408, "nr_orders": 2000, "profit": 3630.0, "file_path": "/Users/matei/git/combinatorial_auction/data/datasets/CAST_test_instance/arbitrary_40.txt", "name": "model_arbitrary_40.txt", "solver": "AOCBaseSolution", "timeout": 300}, {"status": null, "delta_time": 0.09866881370544434, "nr_items": 2408, "nr_orders": 2000, "profit": 3805.0, "file_path": "/Users/matei/git/combinatorial_auction/data/datasets/CAST_test_instance/arbitrary_40.txt", "name": "model_arbitrary_40.txt", "solver": "AOCBaseSolution", "timeout": 300}, {"status": null, "delta_time": 0.09758377075195312, "nr_items": 2408, "nr_orders": 2000, "profit": 3226.0, "file_path": "/Users/matei/git/combinatorial_auction/data/datasets/CAST_test_instance/arbitrary_40.txt", "name": "model_arbitrary_40.txt", "solver": "AOCBaseSolution", "timeout": 300}, {"status": null, "delta_time": 0.10521817207336426, "nr_items": 2408, "nr_orders": 2000, "profit": 3633.0, "file_path": "/Users/matei/git/combinatorial_auction/data/datasets/CAST_test_instance/arbitrary_40.txt", "name": "model_arbitrary_40.txt", "solver": "AOCBaseSolution", "timeout": 300}, {"status": null, "delta_time": 0.10835409164428711, "nr_items": 2408, "nr_orders": 2000, "profit": 3713.0, "file_path": "/Users/matei/git/combinatorial_auction/data/datasets/CAST_test_instance/arbitrary_40.txt", "name": "model_arbitrary_40.txt", "solver": "AOCBaseSolution", "timeout": 300}, {"status": null, "delta_time": 0.10063910484313965, "nr_items": 2408, "nr_orders": 2000, "profit": 3344.0, "file_path": "/Users/matei/git/combinatorial_auction/data/datasets/CAST_test_instance/arbitrary_40.txt", "name": "model_arbitrary_40.txt", "solver": "AOCBaseSolution", "timeout": 300}, {"status": null, "delta_time": 0.10007977485656738, "nr_items": 2408, "nr_orders": 2000, "profit": 3382.0, "file_path": "/Users/matei/git/combinatorial_auction/data/datasets/CAST_test_instance/arbitrary_40.txt", "name": "model_arbitrary_40.txt", "solver": "AOCBaseSolution", "timeout": 300}, {"status": null, "delta_time": 0.09911394119262695, "nr_items": 2408, "nr_orders": 2000, "profit": 3761.0, "file_path": "/Users/matei/git/combinatorial_auction/data/datasets/CAST_test_instance/arbitrary_40.txt", "name": "model_arbitrary_40.txt", "solver": "AOCBaseSolution", "timeout": 300}, {"status": null, "delta_time": 0.10629034042358398, "nr_items": 2408, "nr_orders": 2000, "profit": 3117.0, "file_path": "/Users/matei/git/combinatorial_auction/data/datasets/CAST_test_instance/arbitrary_40.txt", "name": "model_arbitrary_40.txt", "solver": "AOCBaseSolution", "timeout": 300}, {"status": null, "delta_time": 0.0991818904876709, "nr_items": 2408, "nr_orders": 2000, "profit": 3802.0, "file_path": "/Users/matei/git/combinatorial_auction/data/datasets/CAST_test_instance/arbitrary_40.txt", "name": "model_arbitrary_40.txt", "solver": "AOCBaseSolution", "timeout": 300}, {"status": null, "delta_time": 0.09759688377380371, "nr_items": 2408, "nr_orders": 2000, "profit": 3338.0, "file_path": "/Users/matei/git/combinatorial_auction/data/datasets/CAST_test_instance/arbitrary_40.txt", "name": "model_arbitrary_40.txt", "solver": "AOCBaseSolution", "timeout": 300}, {"status": null, "delta_time": 0.10242724418640137, "nr_items": 2408, "nr_orders": 2000, "profit": 3530.0, "file_path": "/Users/matei/git/combinatorial_auction/data/datasets/CAST_test_instance/arbitrary_40.txt", "name": "model_arbitrary_40.txt", "solver": "AOCBaseSolution", "timeout": 300}, {"status": null, "delta_time": 0.1391129493713379, "nr_items": 2409, "nr_orders": 2000, "profit": 3692.0, "file_path": "/Users/matei/git/combinatorial_auction/data/datasets/CAST_test_instance/regions_40.txt", "name": "model_regions_40.txt", "solver": "AOCBaseSolution", "timeout": 300}, {"status": null, "delta_time": 0.12279200553894043, "nr_items": 2409, "nr_orders": 2000, "profit": 3841.0, "file_path": "/Users/matei/git/combinatorial_auction/data/datasets/CAST_test_instance/regions_40.txt", "name": "model_regions_40.txt", "solver": "AOCBaseSolution", "timeout": 300}, {"status": null, "delta_time": 0.12441611289978027, "nr_items": 2409, "nr_orders": 2000, "profit": 3678.0, "file_path": "/Users/matei/git/combinatorial_auction/data/datasets/CAST_test_instance/regions_40.txt", "name": "model_regions_40.txt", "solver": "AOCBaseSolution", "timeout": 300}, {"status": null, "delta_time": 0.10139012336730957, "nr_items": 2409, "nr_orders": 2000, "profit": 3675.0, "file_path": "/Users/matei/git/combinatorial_auction/data/datasets/CAST_test_instance/regions_40.txt", "name": "model_regions_40.txt", "solver": "AOCBaseSolution", "timeout": 300}, {"status": null, "delta_time": 0.10030889511108398, "nr_items": 2409, "nr_orders": 2000, "profit": 3769.0, "file_path": "/Users/matei/git/combinatorial_auction/data/datasets/CAST_test_instance/regions_40.txt", "name": "model_regions_40.txt", "solver": "AOCBaseSolution", "timeout": 300}, {"status": null, "delta_time": 0.10387277603149414, "nr_items": 2409, "nr_orders": 2000, "profit": 3823.0, "file_path": "/Users/matei/git/combinatorial_auction/data/datasets/CAST_test_instance/regions_40.txt", "name": "model_regions_40.txt", "solver": "AOCBaseSolution", "timeout": 300}, {"status": null, "delta_time": 0.11510396003723145, "nr_items": 2409, "nr_orders": 2000, "profit": 3752.0, "file_path": "/Users/matei/git/combinatorial_auction/data/datasets/CAST_test_instance/regions_40.txt", "name": "model_regions_40.txt", "solver": "AOCBaseSolution", "timeout": 300}, {"status": null, "delta_time": 0.10911393165588379, "nr_items": 2409, "nr_orders": 2000, "profit": 3644.0, "file_path": "/Users/matei/git/combinatorial_auction/data/datasets/CAST_test_instance/regions_40.txt", "name": "model_regions_40.txt", "solver": "AOCBaseSolution", "timeout": 300}, {"status": null, "delta_time": 0.12291407585144043, "nr_items": 2409, "nr_orders": 2000, "profit": 3334.0, "file_path": "/Users/matei/git/combinatorial_auction/data/datasets/CAST_test_instance/regions_40.txt", "name": "model_regions_40.txt", "solver": "AOCBaseSolution", "timeout": 300}, {"status": null, "delta_time": 0.10175204277038574, "nr_items": 2409, "nr_orders": 2000, "profit": 3866.0, "file_path": "/Users/matei/git/combinatorial_auction/data/datasets/CAST_test_instance/regions_40.txt", "name": "model_regions_40.txt", "solver": "AOCBaseSolution", "timeout": 300}, {"status": null, "delta_time": 0.09930014610290527, "nr_items": 2409, "nr_orders": 2000, "profit": 3279.0, "file_path": "/Users/matei/git/combinatorial_auction/data/datasets/CAST_test_instance/regions_40.txt", "name": "model_regions_40.txt", "solver": "AOCBaseSolution", "timeout": 300}, {"status": null, "delta_time": 0.10216665267944336, "nr_items": 2409, "nr_orders": 2000, "profit": 3840.0, "file_path": "/Users/matei/git/combinatorial_auction/data/datasets/CAST_test_instance/regions_40.txt", "name": "model_regions_40.txt", "solver": "AOCBaseSolution", "timeout": 300}, {"status": null, "delta_time": 0.10355305671691895, "nr_items": 2409, "nr_orders": 2000, "profit": 3329.0, "file_path": "/Users/matei/git/combinatorial_auction/data/datasets/CAST_test_instance/regions_40.txt", "name": "model_regions_40.txt", "solver": "AOCBaseSolution", "timeout": 300}, {"status": null, "delta_time": 0.10715103149414062, "nr_items": 2409, "nr_orders": 2000, "profit": 3300.0, "file_path": "/Users/matei/git/combinatorial_auction/data/datasets/CAST_test_instance/regions_40.txt", "name": "model_regions_40.txt", "solver": "AOCBaseSolution", "timeout": 300}, {"status": null, "delta_time": 0.1063389778137207, "nr_items": 2409, "nr_orders": 2000, "profit": 3112.0, "file_path": "/Users/matei/git/combinatorial_auction/data/datasets/CAST_test_instance/regions_40.txt", "name": "model_regions_40.txt", "solver": "AOCBaseSolution", "timeout": 300}, {"status": null, "delta_time": 0.09865903854370117, "nr_items": 2409, "nr_orders": 2000, "profit": 3462.0, "file_path": "/Users/matei/git/combinatorial_auction/data/datasets/CAST_test_instance/regions_40.txt", "name": "model_regions_40.txt", "solver": "AOCBaseSolution", "timeout": 300}, {"status": null, "delta_time": 0.11133098602294922, "nr_items": 2409, "nr_orders": 2000, "profit": 3434.0, "file_path": "/Users/matei/git/combinatorial_auction/data/datasets/CAST_test_instance/regions_40.txt", "name": "model_regions_40.txt", "solver": "AOCBaseSolution", "timeout": 300}, {"status": null, "delta_time": 0.1138911247253418, "nr_items": 2409, "nr_orders": 2000, "profit": 3480.0, "file_path": "/Users/matei/git/combinatorial_auction/data/datasets/CAST_test_instance/regions_40.txt", "name": "model_regions_40.txt", "solver": "AOCBaseSolution", "timeout": 300}, {"status": null, "delta_time": 0.11961698532104492, "nr_items": 2409, "nr_orders": 2000, "profit": 3458.0, "file_path": "/Users/matei/git/combinatorial_auction/data/datasets/CAST_test_instance/regions_40.txt", "name": "model_regions_40.txt", "solver": "AOCBaseSolution", "timeout": 300}, {"status": null, "delta_time": 0.1063222885131836, "nr_items": 2409, "nr_orders": 2000, "profit": 3324.0, "file_path": "/Users/matei/git/combinatorial_auction/data/datasets/CAST_test_instance/regions_40.txt", "name": "model_regions_40.txt", "solver": "AOCBaseSolution", "timeout": 300}, {"status": null, "delta_time": 0.10206818580627441, "nr_items": 2409, "nr_orders": 2000, "profit": 3358.0, "file_path": "/Users/matei/git/combinatorial_auction/data/datasets/CAST_test_instance/regions_40.txt", "name": "model_regions_40.txt", "solver": "AOCBaseSolution", "timeout": 300}, {"status": null, "delta_time": 0.11081290245056152, "nr_items": 2409, "nr_orders": 2000, "profit": 3448.0, "file_path": "/Users/matei/git/combinatorial_auction/data/datasets/CAST_test_instance/regions_40.txt", "name": "model_regions_40.txt", "solver": "AOCBaseSolution", "timeout": 300}, {"status": null, "delta_time": 0.1020350456237793, "nr_items": 2409, "nr_orders": 2000, "profit": 3351.0, "file_path": "/Users/matei/git/combinatorial_auction/data/datasets/CAST_test_instance/regions_40.txt", "name": "model_regions_40.txt", "solver": "AOCBaseSolution", "timeout": 300}, {"status": null, "delta_time": 0.10119509696960449, "nr_items": 2409, "nr_orders": 2000, "profit": 3525.0, "file_path": "/Users/matei/git/combinatorial_auction/data/datasets/CAST_test_instance/regions_40.txt", "name": "model_regions_40.txt", "solver": "AOCBaseSolution", "timeout": 300}, {"status": null, "delta_time": 0.11954998970031738, "nr_items": 2409, "nr_orders": 2000, "profit": 3312.0, "file_path": "/Users/matei/git/combinatorial_auction/data/datasets/CAST_test_instance/regions_40.txt", "name": "model_regions_40.txt", "solver": "AOCBaseSolution", "timeout": 300}, {"status": null, "delta_time": 0.1045219898223877, "nr_items": 2409, "nr_orders": 2000, "profit": 3335.0, "file_path": "/Users/matei/git/combinatorial_auction/data/datasets/CAST_test_instance/regions_40.txt", "name": "model_regions_40.txt", "solver": "AOCBaseSolution", "timeout": 300}, {"status": null, "delta_time": 0.10450100898742676, "nr_items": 2409, "nr_orders": 2000, "profit": 3624.0, "file_path": "/Users/matei/git/combinatorial_auction/data/datasets/CAST_test_instance/regions_40.txt", "name": "model_regions_40.txt", "solver": "AOCBaseSolution", "timeout": 300}, {"status": null, "delta_time": 0.09908175468444824, "nr_items": 2409, "nr_orders": 2000, "profit": 3593.0, "file_path": "/Users/matei/git/combinatorial_auction/data/datasets/CAST_test_instance/regions_40.txt", "name": "model_regions_40.txt", "solver": "AOCBaseSolution", "timeout": 300}, {"status": null, "delta_time": 0.15294528007507324, "nr_items": 2409, "nr_orders": 2000, "profit": 3187.0, "file_path": "/Users/matei/git/combinatorial_auction/data/datasets/CAST_test_instance/regions_40.txt", "name": "model_regions_40.txt", "solver": "AOCBaseSolution", "timeout": 300}, {"status": null, "delta_time": 0.15437912940979004, "nr_items": 2409, "nr_orders": 2000, "profit": 3800.0, "file_path": "/Users/matei/git/combinatorial_auction/data/datasets/CAST_test_instance/regions_40.txt", "name": "model_regions_40.txt", "solver": "AOCBaseSolution", "timeout": 300}, {"status": null, "delta_time": 0.11414933204650879, "nr_items": 2465, "nr_orders": 2000, "profit": 3580.0, "file_path": "/Users/matei/git/combinatorial_auction/data/datasets/CAST_test_instance/regions_100.txt", "name": "model_regions_100.txt", "solver": "AOCBaseSolution", "timeout": 300}, {"status": null, "delta_time": 0.12009310722351074, "nr_items": 2465, "nr_orders": 2000, "profit": 3111.0, "file_path": "/Users/matei/git/combinatorial_auction/data/datasets/CAST_test_instance/regions_100.txt", "name": "model_regions_100.txt", "solver": "AOCBaseSolution", "timeout": 300}, {"status": null, "delta_time": 0.1197500228881836, "nr_items": 2465, "nr_orders": 2000, "profit": 3502.0, "file_path": "/Users/matei/git/combinatorial_auction/data/datasets/CAST_test_instance/regions_100.txt", "name": "model_regions_100.txt", "solver": "AOCBaseSolution", "timeout": 300}, {"status": null, "delta_time": 0.12400317192077637, "nr_items": 2465, "nr_orders": 2000, "profit": 3764.0, "file_path": "/Users/matei/git/combinatorial_auction/data/datasets/CAST_test_instance/regions_100.txt", "name": "model_regions_100.txt", "solver": "AOCBaseSolution", "timeout": 300}, {"status": null, "delta_time": 0.11648774147033691, "nr_items": 2465, "nr_orders": 2000, "profit": 3796.0, "file_path": "/Users/matei/git/combinatorial_auction/data/datasets/CAST_test_instance/regions_100.txt", "name": "model_regions_100.txt", "solver": "AOCBaseSolution", "timeout": 300}, {"status": null, "delta_time": 0.12912940979003906, "nr_items": 2465, "nr_orders": 2000, "profit": 3462.0, "file_path": "/Users/matei/git/combinatorial_auction/data/datasets/CAST_test_instance/regions_100.txt", "name": "model_regions_100.txt", "solver": "AOCBaseSolution", "timeout": 300}, {"status": null, "delta_time": 0.12577104568481445, "nr_items": 2465, "nr_orders": 2000, "profit": 3634.0, "file_path": "/Users/matei/git/combinatorial_auction/data/datasets/CAST_test_instance/regions_100.txt", "name": "model_regions_100.txt", "solver": "AOCBaseSolution", "timeout": 300}, {"status": null, "delta_time": 0.1241450309753418, "nr_items": 2465, "nr_orders": 2000, "profit": 3670.0, "file_path": "/Users/matei/git/combinatorial_auction/data/datasets/CAST_test_instance/regions_100.txt", "name": "model_regions_100.txt", "solver": "AOCBaseSolution", "timeout": 300}, {"status": null, "delta_time": 0.12353777885437012, "nr_items": 2465, "nr_orders": 2000, "profit": 3741.0, "file_path": "/Users/matei/git/combinatorial_auction/data/datasets/CAST_test_instance/regions_100.txt", "name": "model_regions_100.txt", "solver": "AOCBaseSolution", "timeout": 300}, {"status": null, "delta_time": 0.13318824768066406, "nr_items": 2465, "nr_orders": 2000, "profit": 3788.0, "file_path": "/Users/matei/git/combinatorial_auction/data/datasets/CAST_test_instance/regions_100.txt", "name": "model_regions_100.txt", "solver": "AOCBaseSolution", "timeout": 300}, {"status": null, "delta_time": 0.15035533905029297, "nr_items": 2465, "nr_orders": 2000, "profit": 3501.0, "file_path": "/Users/matei/git/combinatorial_auction/data/datasets/CAST_test_instance/regions_100.txt", "name": "model_regions_100.txt", "solver": "AOCBaseSolution", "timeout": 300}, {"status": null, "delta_time": 0.18423080444335938, "nr_items": 2465, "nr_orders": 2000, "profit": 3321.0, "file_path": "/Users/matei/git/combinatorial_auction/data/datasets/CAST_test_instance/regions_100.txt", "name": "model_regions_100.txt", "solver": "AOCBaseSolution", "timeout": 300}, {"status": null, "delta_time": 0.1295490264892578, "nr_items": 2465, "nr_orders": 2000, "profit": 3507.0, "file_path": "/Users/matei/git/combinatorial_auction/data/datasets/CAST_test_instance/regions_100.txt", "name": "model_regions_100.txt", "solver": "AOCBaseSolution", "timeout": 300}, {"status": null, "delta_time": 0.11730599403381348, "nr_items": 2465, "nr_orders": 2000, "profit": 3400.0, "file_path": "/Users/matei/git/combinatorial_auction/data/datasets/CAST_test_instance/regions_100.txt", "name": "model_regions_100.txt", "solver": "AOCBaseSolution", "timeout": 300}, {"status": null, "delta_time": 0.1150660514831543, "nr_items": 2465, "nr_orders": 2000, "profit": 3455.0, "file_path": "/Users/matei/git/combinatorial_auction/data/datasets/CAST_test_instance/regions_100.txt", "name": "model_regions_100.txt", "solver": "AOCBaseSolution", "timeout": 300}, {"status": null, "delta_time": 0.11271500587463379, "nr_items": 2465, "nr_orders": 2000, "profit": 3923.0, "file_path": "/Users/matei/git/combinatorial_auction/data/datasets/CAST_test_instance/regions_100.txt", "name": "model_regions_100.txt", "solver": "AOCBaseSolution", "timeout": 300}, {"status": null, "delta_time": 0.11676621437072754, "nr_items": 2465, "nr_orders": 2000, "profit": 3736.0, "file_path": "/Users/matei/git/combinatorial_auction/data/datasets/CAST_test_instance/regions_100.txt", "name": "model_regions_100.txt", "solver": "AOCBaseSolution", "timeout": 300}, {"status": null, "delta_time": 0.11941099166870117, "nr_items": 2465, "nr_orders": 2000, "profit": 3570.0, "file_path": "/Users/matei/git/combinatorial_auction/data/datasets/CAST_test_instance/regions_100.txt", "name": "model_regions_100.txt", "solver": "AOCBaseSolution", "timeout": 300}, {"status": null, "delta_time": 0.1261441707611084, "nr_items": 2465, "nr_orders": 2000, "profit": 3764.0, "file_path": "/Users/matei/git/combinatorial_auction/data/datasets/CAST_test_instance/regions_100.txt", "name": "model_regions_100.txt", "solver": "AOCBaseSolution", "timeout": 300}, {"status": null, "delta_time": 0.1254441738128662, "nr_items": 2465, "nr_orders": 2000, "profit": 3320.0, "file_path": "/Users/matei/git/combinatorial_auction/data/datasets/CAST_test_instance/regions_100.txt", "name": "model_regions_100.txt", "solver": "AOCBaseSolution", "timeout": 300}, {"status": null, "delta_time": 0.12390875816345215, "nr_items": 2465, "nr_orders": 2000, "profit": 2622.0, "file_path": "/Users/matei/git/combinatorial_auction/data/datasets/CAST_test_instance/regions_100.txt", "name": "model_regions_100.txt", "solver": "AOCBaseSolution", "timeout": 300}, {"status": null, "delta_time": 0.1284630298614502, "nr_items": 2465, "nr_orders": 2000, "profit": 3471.0, "file_path": "/Users/matei/git/combinatorial_auction/data/datasets/CAST_test_instance/regions_100.txt", "name": "model_regions_100.txt", "solver": "AOCBaseSolution", "timeout": 300}, {"status": null, "delta_time": 0.12522101402282715, "nr_items": 2465, "nr_orders": 2000, "profit": 3844.0, "file_path": "/Users/matei/git/combinatorial_auction/data/datasets/CAST_test_instance/regions_100.txt", "name": "model_regions_100.txt", "solver": "AOCBaseSolution", "timeout": 300}, {"status": null, "delta_time": 0.1281139850616455, "nr_items": 2465, "nr_orders": 2000, "profit": 3728.0, "file_path": "/Users/matei/git/combinatorial_auction/data/datasets/CAST_test_instance/regions_100.txt", "name": "model_regions_100.txt", "solver": "AOCBaseSolution", "timeout": 300}, {"status": null, "delta_time": 0.11699509620666504, "nr_items": 2465, "nr_orders": 2000, "profit": 3450.0, "file_path": "/Users/matei/git/combinatorial_auction/data/datasets/CAST_test_instance/regions_100.txt", "name": "model_regions_100.txt", "solver": "AOCBaseSolution", "timeout": 300}, {"status": null, "delta_time": 0.1384420394897461, "nr_items": 2465, "nr_orders": 2000, "profit": 3616.0, "file_path": "/Users/matei/git/combinatorial_auction/data/datasets/CAST_test_instance/regions_100.txt", "name": "model_regions_100.txt", "solver": "AOCBaseSolution", "timeout": 300}, {"status": null, "delta_time": 0.14547085762023926, "nr_items": 2465, "nr_orders": 2000, "profit": 3564.0, "file_path": "/Users/matei/git/combinatorial_auction/data/datasets/CAST_test_instance/regions_100.txt", "name": "model_regions_100.txt", "solver": "AOCBaseSolution", "timeout": 300}, {"status": null, "delta_time": 0.15554308891296387, "nr_items": 2465, "nr_orders": 2000, "profit": 3273.0, "file_path": "/Users/matei/git/combinatorial_auction/data/datasets/CAST_test_instance/regions_100.txt", "name": "model_regions_100.txt", "solver": "AOCBaseSolution", "timeout": 300}, {"status": null, "delta_time": 0.1443498134613037, "nr_items": 2465, "nr_orders": 2000, "profit": 3756.0, "file_path": "/Users/matei/git/combinatorial_auction/data/datasets/CAST_test_instance/regions_100.txt", "name": "model_regions_100.txt", "solver": "AOCBaseSolution", "timeout": 300}, {"status": null, "delta_time": 0.12504911422729492, "nr_items": 2465, "nr_orders": 2000, "profit": 3564.0, "file_path": "/Users/matei/git/combinatorial_auction/data/datasets/CAST_test_instance/regions_100.txt", "name": "model_regions_100.txt", "solver": "AOCBaseSolution", "timeout": 300}, {"status": null, "delta_time": 0.11393904685974121, "nr_items": 2466, "nr_orders": 2000, "profit": 3441.0, "file_path": "/Users/matei/git/combinatorial_auction/data/datasets/CAST_test_instance/arbitrary_100.txt", "name": "model_arbitrary_100.txt", "solver": "AOCBaseSolution", "timeout": 300}, {"status": null, "delta_time": 0.10132026672363281, "nr_items": 2466, "nr_orders": 2000, "profit": 3286.0, "file_path": "/Users/matei/git/combinatorial_auction/data/datasets/CAST_test_instance/arbitrary_100.txt", "name": "model_arbitrary_100.txt", "solver": "AOCBaseSolution", "timeout": 300}, {"status": null, "delta_time": 0.11774086952209473, "nr_items": 2466, "nr_orders": 2000, "profit": 3318.0, "file_path": "/Users/matei/git/combinatorial_auction/data/datasets/CAST_test_instance/arbitrary_100.txt", "name": "model_arbitrary_100.txt", "solver": "AOCBaseSolution", "timeout": 300}, {"status": null, "delta_time": 0.11548686027526855, "nr_items": 2466, "nr_orders": 2000, "profit": 3404.0, "file_path": "/Users/matei/git/combinatorial_auction/data/datasets/CAST_test_instance/arbitrary_100.txt", "name": "model_arbitrary_100.txt", "solver": "AOCBaseSolution", "timeout": 300}, {"status": null, "delta_time": 0.11453700065612793, "nr_items": 2466, "nr_orders": 2000, "profit": 3888.0, "file_path": "/Users/matei/git/combinatorial_auction/data/datasets/CAST_test_instance/arbitrary_100.txt", "name": "model_arbitrary_100.txt", "solver": "AOCBaseSolution", "timeout": 300}, {"status": null, "delta_time": 0.11392378807067871, "nr_items": 2466, "nr_orders": 2000, "profit": 3918.0, "file_path": "/Users/matei/git/combinatorial_auction/data/datasets/CAST_test_instance/arbitrary_100.txt", "name": "model_arbitrary_100.txt", "solver": "AOCBaseSolution", "timeout": 300}, {"status": null, "delta_time": 0.11669111251831055, "nr_items": 2466, "nr_orders": 2000, "profit": 3604.0, "file_path": "/Users/matei/git/combinatorial_auction/data/datasets/CAST_test_instance/arbitrary_100.txt", "name": "model_arbitrary_100.txt", "solver": "AOCBaseSolution", "timeout": 300}, {"status": null, "delta_time": 0.12361574172973633, "nr_items": 2466, "nr_orders": 2000, "profit": 3144.0, "file_path": "/Users/matei/git/combinatorial_auction/data/datasets/CAST_test_instance/arbitrary_100.txt", "name": "model_arbitrary_100.txt", "solver": "AOCBaseSolution", "timeout": 300}, {"status": null, "delta_time": 0.11196017265319824, "nr_items": 2466, "nr_orders": 2000, "profit": 3603.0, "file_path": "/Users/matei/git/combinatorial_auction/data/datasets/CAST_test_instance/arbitrary_100.txt", "name": "model_arbitrary_100.txt", "solver": "AOCBaseSolution", "timeout": 300}, {"status": null, "delta_time": 0.11327385902404785, "nr_items": 2466, "nr_orders": 2000, "profit": 3609.0, "file_path": "/Users/matei/git/combinatorial_auction/data/datasets/CAST_test_instance/arbitrary_100.txt", "name": "model_arbitrary_100.txt", "solver": "AOCBaseSolution", "timeout": 300}, {"status": null, "delta_time": 0.11350512504577637, "nr_items": 2466, "nr_orders": 2000, "profit": 3581.0, "file_path": "/Users/matei/git/combinatorial_auction/data/datasets/CAST_test_instance/arbitrary_100.txt", "name": "model_arbitrary_100.txt", "solver": "AOCBaseSolution", "timeout": 300}, {"status": null, "delta_time": 0.09764409065246582, "nr_items": 2466, "nr_orders": 2000, "profit": 3528.0, "file_path": "/Users/matei/git/combinatorial_auction/data/datasets/CAST_test_instance/arbitrary_100.txt", "name": "model_arbitrary_100.txt", "solver": "AOCBaseSolution", "timeout": 300}, {"status": null, "delta_time": 0.1061549186706543, "nr_items": 2466, "nr_orders": 2000, "profit": 3441.0, "file_path": "/Users/matei/git/combinatorial_auction/data/datasets/CAST_test_instance/arbitrary_100.txt", "name": "model_arbitrary_100.txt", "solver": "AOCBaseSolution", "timeout": 300}, {"status": null, "delta_time": 0.09373188018798828, "nr_items": 2466, "nr_orders": 2000, "profit": 3325.0, "file_path": "/Users/matei/git/combinatorial_auction/data/datasets/CAST_test_instance/arbitrary_100.txt", "name": "model_arbitrary_100.txt", "solver": "AOCBaseSolution", "timeout": 300}, {"status": null, "delta_time": 0.10483598709106445, "nr_items": 2466, "nr_orders": 2000, "profit": 3582.0, "file_path": "/Users/matei/git/combinatorial_auction/data/datasets/CAST_test_instance/arbitrary_100.txt", "name": "model_arbitrary_100.txt", "solver": "AOCBaseSolution", "timeout": 300}, {"status": null, "delta_time": 0.11484694480895996, "nr_items": 2466, "nr_orders": 2000, "profit": 3077.0, "file_path": "/Users/matei/git/combinatorial_auction/data/datasets/CAST_test_instance/arbitrary_100.txt", "name": "model_arbitrary_100.txt", "solver": "AOCBaseSolution", "timeout": 300}, {"status": null, "delta_time": 0.11470484733581543, "nr_items": 2466, "nr_orders": 2000, "profit": 3820.0, "file_path": "/Users/matei/git/combinatorial_auction/data/datasets/CAST_test_instance/arbitrary_100.txt", "name": "model_arbitrary_100.txt", "solver": "AOCBaseSolution", "timeout": 300}, {"status": null, "delta_time": 0.09877777099609375, "nr_items": 2466, "nr_orders": 2000, "profit": 3915.0, "file_path": "/Users/matei/git/combinatorial_auction/data/datasets/CAST_test_instance/arbitrary_100.txt", "name": "model_arbitrary_100.txt", "solver": "AOCBaseSolution", "timeout": 300}, {"status": null, "delta_time": 0.11884307861328125, "nr_items": 2466, "nr_orders": 2000, "profit": 3551.0, "file_path": "/Users/matei/git/combinatorial_auction/data/datasets/CAST_test_instance/arbitrary_100.txt", "name": "model_arbitrary_100.txt", "solver": "AOCBaseSolution", "timeout": 300}, {"status": null, "delta_time": 0.11300110816955566, "nr_items": 2466, "nr_orders": 2000, "profit": 3511.0, "file_path": "/Users/matei/git/combinatorial_auction/data/datasets/CAST_test_instance/arbitrary_100.txt", "name": "model_arbitrary_100.txt", "solver": "AOCBaseSolution", "timeout": 300}, {"status": null, "delta_time": 0.11938619613647461, "nr_items": 2466, "nr_orders": 2000, "profit": 3824.0, "file_path": "/Users/matei/git/combinatorial_auction/data/datasets/CAST_test_instance/arbitrary_100.txt", "name": "model_arbitrary_100.txt", "solver": "AOCBaseSolution", "timeout": 300}, {"status": null, "delta_time": 0.11899733543395996, "nr_items": 2466, "nr_orders": 2000, "profit": 3603.0, "file_path": "/Users/matei/git/combinatorial_auction/data/datasets/CAST_test_instance/arbitrary_100.txt", "name": "model_arbitrary_100.txt", "solver": "AOCBaseSolution", "timeout": 300}, {"status": null, "delta_time": 0.1098477840423584, "nr_items": 2466, "nr_orders": 2000, "profit": 3307.0, "file_path": "/Users/matei/git/combinatorial_auction/data/datasets/CAST_test_instance/arbitrary_100.txt", "name": "model_arbitrary_100.txt", "solver": "AOCBaseSolution", "timeout": 300}, {"status": null, "delta_time": 0.10783100128173828, "nr_items": 2466, "nr_orders": 2000, "profit": 3427.0, "file_path": "/Users/matei/git/combinatorial_auction/data/datasets/CAST_test_instance/arbitrary_100.txt", "name": "model_arbitrary_100.txt", "solver": "AOCBaseSolution", "timeout": 300}, {"status": null, "delta_time": 0.10600900650024414, "nr_items": 2466, "nr_orders": 2000, "profit": 3683.0, "file_path": "/Users/matei/git/combinatorial_auction/data/datasets/CAST_test_instance/arbitrary_100.txt", "name": "model_arbitrary_100.txt", "solver": "AOCBaseSolution", "timeout": 300}, {"status": null, "delta_time": 0.10393691062927246, "nr_items": 2466, "nr_orders": 2000, "profit": 3525.0, "file_path": "/Users/matei/git/combinatorial_auction/data/datasets/CAST_test_instance/arbitrary_100.txt", "name": "model_arbitrary_100.txt", "solver": "AOCBaseSolution", "timeout": 300}, {"status": null, "delta_time": 0.10415315628051758, "nr_items": 2466, "nr_orders": 2000, "profit": 3459.0, "file_path": "/Users/matei/git/combinatorial_auction/data/datasets/CAST_test_instance/arbitrary_100.txt", "name": "model_arbitrary_100.txt", "solver": "AOCBaseSolution", "timeout": 300}, {"status": null, "delta_time": 0.11160993576049805, "nr_items": 2466, "nr_orders": 2000, "profit": 3602.0, "file_path": "/Users/matei/git/combinatorial_auction/data/datasets/CAST_test_instance/arbitrary_100.txt", "name": "model_arbitrary_100.txt", "solver": "AOCBaseSolution", "timeout": 300}, {"status": null, "delta_time": 0.10413694381713867, "nr_items": 2466, "nr_orders": 2000, "profit": 3673.0, "file_path": "/Users/matei/git/combinatorial_auction/data/datasets/CAST_test_instance/arbitrary_100.txt", "name": "model_arbitrary_100.txt", "solver": "AOCBaseSolution", "timeout": 300}, {"status": null, "delta_time": 0.09847784042358398, "nr_items": 2466, "nr_orders": 2000, "profit": 3175.0, "file_path": "/Users/matei/git/combinatorial_auction/data/datasets/CAST_test_instance/arbitrary_100.txt", "name": "model_arbitrary_100.txt", "solver": "AOCBaseSolution", "timeout": 300}]}